{
  "timestamp": "2026-06-29T13:08:59.642Z",
  "version": 1,
  "kaminoTvl": 1201447621,
  "kaminoTvlHistory": [
    {
      "date": 1780185600,
      "tvl": 1452364062
    },
    {
      "date": 1780272000,
      "tvl": 1453008250
    },
    {
      "date": 1780358400,
      "tvl": 1439830281
    },
    {
      "date": 1780444800,
      "tvl": 1373405390
    },
    {
      "date": 1780531200,
      "tvl": 1409698896
    },
    {
      "date": 1780617600,
      "tvl": 1479637430
    },
    {
      "date": 1780704000,
      "tvl": 1408284160
    },
    {
      "date": 1780790400,
      "tvl": 1433733781
    },
    {
      "date": 1780876800,
      "tvl": 1481809304
    },
    {
      "date": 1780963200,
      "tvl": 1467261257
    },
    {
      "date": 1781049600,
      "tvl": 1441831906
    },
    {
      "date": 1781136000,
      "tvl": 1156057667
    },
    {
      "date": 1781222400,
      "tvl": 1175719563
    },
    {
      "date": 1781308800,
      "tvl": 1207866857
    },
    {
      "date": 1781395200,
      "tvl": 1196684051
    },
    {
      "date": 1781481600,
      "tvl": 1237463876
    },
    {
      "date": 1781568000,
      "tvl": 1220133558
    },
    {
      "date": 1781654400,
      "tvl": 1235747249
    },
    {
      "date": 1781740800,
      "tvl": 1200422870
    },
    {
      "date": 1781827200,
      "tvl": 1209121932
    },
    {
      "date": 1781913600,
      "tvl": 1205961192
    },
    {
      "date": 1782000000,
      "tvl": 1232259793
    },
    {
      "date": 1782086400,
      "tvl": 1230883367
    },
    {
      "date": 1782172800,
      "tvl": 1230153829
    },
    {
      "date": 1782259200,
      "tvl": 1208415829
    },
    {
      "date": 1782345600,
      "tvl": 1190848142
    },
    {
      "date": 1782432000,
      "tvl": 1160842796
    },
    {
      "date": 1782518400,
      "tvl": 1200762665
    },
    {
      "date": 1782604800,
      "tvl": 1163161289
    },
    {
      "date": 1782691200,
      "tvl": 1192874480
    },
    {
      "date": 1782734207,
      "tvl": 1201447621
    }
  ],
  "competitors": [
    {
      "twitterHandle": "Kamino",
      "displayName": "Kamino",
      "defiLlamaSlug": "kamino",
      "profilePicture": "https://pbs.twimg.com/profile_images/1999411256155938818/lAOSJHuf_normal.jpg",
      "tvl": 1201447621,
      "tvlHistory": [
        {
          "date": 1780185600,
          "tvl": 1452364062
        },
        {
          "date": 1780272000,
          "tvl": 1453008250
        },
        {
          "date": 1780358400,
          "tvl": 1439830281
        },
        {
          "date": 1780444800,
          "tvl": 1373405390
        },
        {
          "date": 1780531200,
          "tvl": 1409698896
        },
        {
          "date": 1780617600,
          "tvl": 1479637430
        },
        {
          "date": 1780704000,
          "tvl": 1408284160
        },
        {
          "date": 1780790400,
          "tvl": 1433733781
        },
        {
          "date": 1780876800,
          "tvl": 1481809304
        },
        {
          "date": 1780963200,
          "tvl": 1467261257
        },
        {
          "date": 1781049600,
          "tvl": 1441831906
        },
        {
          "date": 1781136000,
          "tvl": 1156057667
        },
        {
          "date": 1781222400,
          "tvl": 1175719563
        },
        {
          "date": 1781308800,
          "tvl": 1207866857
        },
        {
          "date": 1781395200,
          "tvl": 1196684051
        },
        {
          "date": 1781481600,
          "tvl": 1237463876
        },
        {
          "date": 1781568000,
          "tvl": 1220133558
        },
        {
          "date": 1781654400,
          "tvl": 1235747249
        },
        {
          "date": 1781740800,
          "tvl": 1200422870
        },
        {
          "date": 1781827200,
          "tvl": 1209121932
        },
        {
          "date": 1781913600,
          "tvl": 1205961192
        },
        {
          "date": 1782000000,
          "tvl": 1232259793
        },
        {
          "date": 1782086400,
          "tvl": 1230883367
        },
        {
          "date": 1782172800,
          "tvl": 1230153829
        },
        {
          "date": 1782259200,
          "tvl": 1208415829
        },
        {
          "date": 1782345600,
          "tvl": 1190848142
        },
        {
          "date": 1782432000,
          "tvl": 1160842796
        },
        {
          "date": 1782518400,
          "tvl": 1200762665
        },
        {
          "date": 1782604800,
          "tvl": 1163161289
        },
        {
          "date": 1782691200,
          "tvl": 1192874480
        },
        {
          "date": 1782734207,
          "tvl": 1201447621
        }
      ],
      "aiSummary": "",
      "tweets": [
        {
          "id": "2070536176612827301",
          "fullText": "Kamino's OnRe market is one of the largest RWA markets in DeFi.\n\n$160M+ Market Size. $50M+ Borrowed. 1.1K Active Loans.\n\nReal-world assets scale on Kamino. https://t.co/nPYugF1BIE",
          "createdAt": "Fri Jun 26 15:54:27 +0000 2026",
          "twitterUrl": "https://twitter.com/kamino/status/2070536176612827301",
          "likeCount": 98,
          "bookmarkCount": 4,
          "retweetCount": 12,
          "replyCount": 15,
          "viewCount": 12009,
          "thumbnailUrl": "https://pbs.twimg.com/media/HLwFrhyaUAANmLC.jpg"
        },
        {
          "id": "2070175821092802760",
          "fullText": "Kamino secures billions in user funds and manages risk and security accordingly.\n\nBelow, we detail Kamino's full operational security surface and how it stops a malicious change before it ever executes:",
          "createdAt": "Thu Jun 25 16:02:32 +0000 2026",
          "twitterUrl": "https://twitter.com/kamino/status/2070175821092802760",
          "likeCount": 49,
          "bookmarkCount": 8,
          "retweetCount": 3,
          "replyCount": 5,
          "viewCount": 7224
        },
        {
          "id": "2069847839526604919",
          "fullText": "The PRIME Market by @HastraFi, backed by home equity loans from Nasdaq-listed @Figure, grew to an all-time high of $630M in market size.\n\nKamino's credit infrastructure is built to scale real-world assets on Solana.\n\nRead the full case study below:",
          "createdAt": "Wed Jun 24 18:19:15 +0000 2026",
          "twitterUrl": "https://twitter.com/kamino/status/2069847839526604919",
          "likeCount": 38,
          "bookmarkCount": 0,
          "retweetCount": 5,
          "replyCount": 14,
          "viewCount": 7898
        },
        {
          "id": "2067299661627465761",
          "fullText": "New updates are live in the OnRe Market on Kamino.  \n\n• ONyc LTV has increased from 60% → 66%, enabling up to 2.9x leverage for all ONyc looping positions. \n• PT-ONyc is live: current fixed 12% yield, maturing 10 Sep. https://t.co/bAqZosyzHP",
          "createdAt": "Wed Jun 17 17:33:42 +0000 2026",
          "twitterUrl": "https://twitter.com/kamino/status/2067299661627465761",
          "likeCount": 69,
          "bookmarkCount": 5,
          "retweetCount": 6,
          "replyCount": 7,
          "viewCount": 4404,
          "thumbnailUrl": "https://pbs.twimg.com/media/HLCGFhpWcAAhU7m.jpg"
        },
        {
          "id": "2070515404561096957",
          "fullText": "$DRAM is tradable 24/7 on Kamino Swap.  \n\nEach token is backed 1:1 by a Roundhill Memory ETF share and redeemable through @Backpack, live on Solana via @sunrise.",
          "createdAt": "Fri Jun 26 14:31:55 +0000 2026",
          "twitterUrl": "https://twitter.com/kamino/status/2070515404561096957",
          "likeCount": 93,
          "bookmarkCount": 4,
          "retweetCount": 10,
          "replyCount": 6,
          "viewCount": 9883
        }
      ]
    },
    {
      "twitterHandle": "aave",
      "displayName": "Aave",
      "defiLlamaSlug": "aave-v3",
      "profilePicture": "https://pbs.twimg.com/profile_images/1808921860781821952/CmtvkzWo_normal.png",
      "tvl": 21552071734.535698,
      "tvlHistory": [
        {
          "date": 1780185600,
          "tvl": 13326197278
        },
        {
          "date": 1780272000,
          "tvl": 13321699811
        },
        {
          "date": 1780358400,
          "tvl": 13177806662
        },
        {
          "date": 1780444800,
          "tvl": 12344846361
        },
        {
          "date": 1780531200,
          "tvl": 12038657448
        },
        {
          "date": 1780617600,
          "tvl": 12077282404
        },
        {
          "date": 1780704000,
          "tvl": 11472366264
        },
        {
          "date": 1780790400,
          "tvl": 11345083647
        },
        {
          "date": 1780876800,
          "tvl": 11939503887
        },
        {
          "date": 1780963200,
          "tvl": 11896541183
        },
        {
          "date": 1781049600,
          "tvl": 11557464731
        },
        {
          "date": 1781136000,
          "tvl": 11418337368
        },
        {
          "date": 1781222400,
          "tvl": 11621020940
        },
        {
          "date": 1781308800,
          "tvl": 11766097241
        },
        {
          "date": 1781395200,
          "tvl": 11883145443
        },
        {
          "date": 1781481600,
          "tvl": 12159586869
        },
        {
          "date": 1781568000,
          "tvl": 12422853077
        },
        {
          "date": 1781654400,
          "tvl": 12639902565
        },
        {
          "date": 1781740800,
          "tvl": 12420429472
        },
        {
          "date": 1781827200,
          "tvl": 12273544858
        },
        {
          "date": 1781913600,
          "tvl": 12336176030
        },
        {
          "date": 1782000000,
          "tvl": 12529365080
        },
        {
          "date": 1782086400,
          "tvl": 12368377021
        },
        {
          "date": 1782172800,
          "tvl": 12455770819
        },
        {
          "date": 1782259200,
          "tvl": 12182009751
        },
        {
          "date": 1782345600,
          "tvl": 11885108893
        },
        {
          "date": 1782432000,
          "tvl": 11651983029
        },
        {
          "date": 1782518400,
          "tvl": 11847850361
        },
        {
          "date": 1782604800,
          "tvl": 11883373469
        },
        {
          "date": 1782691200,
          "tvl": 11827138515
        },
        {
          "date": 1782733835,
          "tvl": 11862381927
        }
      ],
      "aiSummary": "",
      "tweets": [
        {
          "id": "2070506262035321143",
          "fullText": "Gold-backed loans using @tethergold on Aave V4 are at an all-time high. https://t.co/YOfAsRdBF6",
          "createdAt": "Fri Jun 26 13:55:35 +0000 2026",
          "twitterUrl": "https://twitter.com/aave/status/2070506262035321143",
          "likeCount": 386,
          "bookmarkCount": 15,
          "retweetCount": 43,
          "replyCount": 19,
          "viewCount": 65506,
          "thumbnailUrl": "https://pbs.twimg.com/media/HLvqczJX0AAbuqq.jpg"
        },
        {
          "id": "2069485205950218609",
          "fullText": "USDT by @tether on Aave's @ethereum Core market is approaching $3 billion deposits. https://t.co/hVHWoRDsMv",
          "createdAt": "Tue Jun 23 18:18:16 +0000 2026",
          "twitterUrl": "https://twitter.com/aave/status/2069485205950218609",
          "likeCount": 283,
          "bookmarkCount": 2,
          "retweetCount": 41,
          "replyCount": 18,
          "viewCount": 34825,
          "thumbnailUrl": "https://pbs.twimg.com/media/HLhJW7qXIAAuPVS.png"
        },
        {
          "id": "2069420918841974986",
          "fullText": "mGLOBAL is live on Aave Horizon.\n\nIssued by @MidasRWA, mGLOBAL tracks a strategy from @FasanaraCapital, a $6B institutional asset manager with a 10+ year track record.\n\nQualified institutions can use it as collateral to borrow stablecoins while keeping the underlying exposure. https://t.co/yGVi5cLhbt",
          "createdAt": "Tue Jun 23 14:02:49 +0000 2026",
          "twitterUrl": "https://twitter.com/aave/status/2069420918841974986",
          "likeCount": 206,
          "bookmarkCount": 7,
          "retweetCount": 32,
          "replyCount": 20,
          "viewCount": 56904,
          "thumbnailUrl": "https://pbs.twimg.com/media/HLgJ0vOXYAAJVRs.png"
        },
        {
          "id": "2069029904725770527",
          "fullText": "Aave V4 crossed $200 million deposits. https://t.co/5zNN3QYU0T",
          "createdAt": "Mon Jun 22 12:09:04 +0000 2026",
          "twitterUrl": "https://twitter.com/aave/status/2069029904725770527",
          "likeCount": 344,
          "bookmarkCount": 9,
          "retweetCount": 35,
          "replyCount": 33,
          "viewCount": 111566,
          "thumbnailUrl": "https://pbs.twimg.com/amplify_video_thumb/2069029741387014144/img/8oLEiiwsW_t633k-.jpg"
        },
        {
          "id": "2067978305379226029",
          "fullText": "A new Aave V4 security audit by @chain_security is now available, covering the V4 Tokenization Spoke.\n\nReview it below. https://t.co/WyO4W1RME8",
          "createdAt": "Fri Jun 19 14:30:23 +0000 2026",
          "twitterUrl": "https://twitter.com/aave/status/2067978305379226029",
          "likeCount": 232,
          "bookmarkCount": 7,
          "retweetCount": 82,
          "replyCount": 14,
          "viewCount": 25401,
          "thumbnailUrl": "https://pbs.twimg.com/media/HLLu9j4XoAAUsbK.jpg"
        }
      ]
    },
    {
      "twitterHandle": "0xfluid",
      "displayName": "Fluid 🌊",
      "defiLlamaSlug": "fluid-lending",
      "profilePicture": "https://pbs.twimg.com/profile_images/1712332669697024001/xgs6LB3Y_normal.png",
      "tvl": 1304105169.77719,
      "tvlHistory": [
        {
          "date": 1780185600,
          "tvl": 753676172
        },
        {
          "date": 1780272000,
          "tvl": 727284034
        },
        {
          "date": 1780358400,
          "tvl": 664849373
        },
        {
          "date": 1780444800,
          "tvl": 642242295
        },
        {
          "date": 1780531200,
          "tvl": 623602141
        },
        {
          "date": 1780617600,
          "tvl": 603185941
        },
        {
          "date": 1780704000,
          "tvl": 577948759
        },
        {
          "date": 1780790400,
          "tvl": 572575522
        },
        {
          "date": 1780876800,
          "tvl": 593782527
        },
        {
          "date": 1780963200,
          "tvl": 598478788
        },
        {
          "date": 1781049600,
          "tvl": 588473706
        },
        {
          "date": 1781136000,
          "tvl": 583198714
        },
        {
          "date": 1781222400,
          "tvl": 583777135
        },
        {
          "date": 1781308800,
          "tvl": 583604014
        },
        {
          "date": 1781395200,
          "tvl": 588672795
        },
        {
          "date": 1781481600,
          "tvl": 592980184
        },
        {
          "date": 1781568000,
          "tvl": 595675325
        },
        {
          "date": 1781654400,
          "tvl": 600131541
        },
        {
          "date": 1781740800,
          "tvl": 589490720
        },
        {
          "date": 1781827200,
          "tvl": 583568396
        },
        {
          "date": 1781913600,
          "tvl": 577533530
        },
        {
          "date": 1782000000,
          "tvl": 595050880
        },
        {
          "date": 1782086400,
          "tvl": 587865715
        },
        {
          "date": 1782172800,
          "tvl": 591474423
        },
        {
          "date": 1782259200,
          "tvl": 577659952
        },
        {
          "date": 1782345600,
          "tvl": 578065717
        },
        {
          "date": 1782432000,
          "tvl": 580317517
        },
        {
          "date": 1782518400,
          "tvl": 581484737
        },
        {
          "date": 1782604800,
          "tvl": 591469804
        },
        {
          "date": 1782691200,
          "tvl": 588775533
        },
        {
          "date": 1782733655,
          "tvl": 599282654
        }
      ],
      "aiSummary": "",
      "tweets": [
        {
          "id": "2069842473443115333",
          "fullText": "There's high borrowing demand on Fluid. \nThat means lending rates are up.\n\n→ USDC: 7.19% APR\n→ USDT: 9.64% APR\n→ GHO: 6.52% APR\n\nMore borrowers. Higher yields for lenders. Capital working harder.\n\nStay Fluid → https://t.co/esLQmr1iuN",
          "createdAt": "Wed Jun 24 17:57:56 +0000 2026",
          "twitterUrl": "https://twitter.com/0xfluid/status/2069842473443115333",
          "likeCount": 38,
          "bookmarkCount": 4,
          "retweetCount": 4,
          "replyCount": 3,
          "viewCount": 7562
        },
        {
          "id": "2066837971345735978",
          "fullText": "NYC recap🗽\n\n@smykjain took the @ethconf stage to highlight:\n→ Our 8 years building. From @Instadapp to Fluid\n→ Institutions and protocols are choosing Fluid infra to launch their own onchain products like lending markets, DEXes, liquidity for stablecoins and RWA.\n\nFluid https://t.co/vsrbxVoR5v",
          "createdAt": "Tue Jun 16 10:59:07 +0000 2026",
          "twitterUrl": "https://twitter.com/0xfluid/status/2066837971345735978",
          "likeCount": 65,
          "bookmarkCount": 4,
          "retweetCount": 11,
          "replyCount": 5,
          "viewCount": 4821,
          "thumbnailUrl": "https://pbs.twimg.com/media/HK7iKaUb0AAq_se.jpg"
        },
        {
          "id": "2066532798546997705",
          "fullText": "Stablecoins need Fluid 🌊",
          "createdAt": "Mon Jun 15 14:46:28 +0000 2026",
          "twitterUrl": "https://twitter.com/0xfluid/status/2066532798546997705",
          "likeCount": 41,
          "bookmarkCount": 3,
          "retweetCount": 7,
          "replyCount": 3,
          "viewCount": 2813
        },
        {
          "id": "2069434725119459758",
          "fullText": "PST is live on Fluid 🌊\n\n@humafinance’s PayFi asset backed by real-world payments: now accesses DEX liquidity and borrowing on Fluid through a single integration.\n\nPST is among the first assets leveraging Fluid’s Liquidity as a Service infrastructure designed to bring scalable https://t.co/jS7sl1Ow4y",
          "createdAt": "Tue Jun 23 14:57:41 +0000 2026",
          "twitterUrl": "https://twitter.com/0xfluid/status/2069434725119459758",
          "likeCount": 41,
          "bookmarkCount": 4,
          "retweetCount": 8,
          "replyCount": 7,
          "viewCount": 5229,
          "thumbnailUrl": "https://pbs.twimg.com/media/HLgb6lCa4AAWiIt.jpg"
        },
        {
          "id": "2069416391753785537",
          "fullText": "Fluid is joining Hashi, @SuiNetwork’s native Bitcoin finance primitive.\n\n$BTC stays on its own chain. Verifiable contracts make it productive.\nFluid brings the credit markets with capital-efficiency built for institutional scale.\n\nSoon 🌊 https://t.co/NV6XM5zzA8",
          "createdAt": "Tue Jun 23 13:44:50 +0000 2026",
          "twitterUrl": "https://twitter.com/0xfluid/status/2069416391753785537",
          "likeCount": 119,
          "bookmarkCount": 8,
          "retweetCount": 25,
          "replyCount": 8,
          "viewCount": 15247,
          "thumbnailUrl": "https://pbs.twimg.com/media/HLgLPaFawAAC4Qp.jpg"
        }
      ]
    },
    {
      "twitterHandle": "jup_lend",
      "displayName": "Jupiter Lend",
      "defiLlamaSlug": "jupiter-lend",
      "profilePicture": "https://pbs.twimg.com/profile_images/2007318464030228480/4x6SH7gB_normal.jpg",
      "tvl": 888091177.49994,
      "tvlHistory": [
        {
          "date": 1780185600,
          "tvl": 953881735
        },
        {
          "date": 1780272000,
          "tvl": 949389527
        },
        {
          "date": 1780358400,
          "tvl": 935291947
        },
        {
          "date": 1780444800,
          "tvl": 902985087
        },
        {
          "date": 1780531200,
          "tvl": 894981452
        },
        {
          "date": 1780617600,
          "tvl": 874791418
        },
        {
          "date": 1780704000,
          "tvl": 843982907
        },
        {
          "date": 1780790400,
          "tvl": 843539301
        },
        {
          "date": 1780876800,
          "tvl": 873699087
        },
        {
          "date": 1780963200,
          "tvl": 868790879
        },
        {
          "date": 1781049600,
          "tvl": 825203187
        },
        {
          "date": 1781136000,
          "tvl": 778075950
        },
        {
          "date": 1781222400,
          "tvl": 821988585
        },
        {
          "date": 1781308800,
          "tvl": 872235426
        },
        {
          "date": 1781395200,
          "tvl": 896480907
        },
        {
          "date": 1781481600,
          "tvl": 906754936
        },
        {
          "date": 1781568000,
          "tvl": 914932294
        },
        {
          "date": 1781654400,
          "tvl": 912462056
        },
        {
          "date": 1781740800,
          "tvl": 856968222
        },
        {
          "date": 1781827200,
          "tvl": 887772507
        },
        {
          "date": 1781913600,
          "tvl": 872940971
        },
        {
          "date": 1782000000,
          "tvl": 899077697
        },
        {
          "date": 1782086400,
          "tvl": 894311209
        },
        {
          "date": 1782172800,
          "tvl": 855243858
        },
        {
          "date": 1782259200,
          "tvl": 868395286
        },
        {
          "date": 1782345600,
          "tvl": 860996423
        },
        {
          "date": 1782432000,
          "tvl": 857936937
        },
        {
          "date": 1782518400,
          "tvl": 878597594
        },
        {
          "date": 1782604800,
          "tvl": 874454566
        },
        {
          "date": 1782691200,
          "tvl": 881608544
        },
        {
          "date": 1782735515,
          "tvl": 888091177
        }
      ],
      "aiSummary": "",
      "tweets": [
        {
          "id": "2069254639443419471",
          "fullText": "Transparency really matters in DeFi.\n\nThat’s why Jupiter Lend actively maintains our Transparency Page with:\n• Every audit and formal verification\n• Published risk research\n• Oracle integrations\n• Links to our multi-sigs\n\nSee it all for yourself: https://t.co/oFiVKLErOz https://t.co/FAzDtZ0aR3",
          "createdAt": "Tue Jun 23 03:02:05 +0000 2026",
          "twitterUrl": "https://twitter.com/jup_lend/status/2069254639443419471",
          "likeCount": 64,
          "bookmarkCount": 2,
          "retweetCount": 9,
          "replyCount": 2,
          "viewCount": 5959,
          "thumbnailUrl": "https://pbs.twimg.com/media/HLd1t75bQAAiHSI.jpg"
        },
        {
          "id": "2068591084671012989",
          "fullText": "The simplest upgrade to your strategy is earning on your stables. \n\nMost people already earn on their SOL. \n\nBut any USDC sitting between trades is the next easy target.\n\nHold JUICED or jlUSDC, so your capital builds until your next entry. \n\nEvery small edge compounds. https://t.co/Xrd2demVRr",
          "createdAt": "Sun Jun 21 07:05:21 +0000 2026",
          "twitterUrl": "https://twitter.com/jup_lend/status/2068591084671012989",
          "likeCount": 60,
          "bookmarkCount": 1,
          "retweetCount": 5,
          "replyCount": 4,
          "viewCount": 2188,
          "thumbnailUrl": "https://pbs.twimg.com/media/HLUaEVqa4AAdOT0.jpg"
        },
        {
          "id": "2071477143968907585",
          "fullText": "You can start earning immediately on 2 assets that everyone owns:\n\n1. Lend your stables for up to 5.6% APY on Jupiter Lend.\n\nYou can even swap directly into these yield-bearing positions by buying tokens like JUICED.\n\n2. Stake your SOL with Jupiter's validator for ~5.5% APY. https://t.co/t2wzG2hkyp",
          "createdAt": "Mon Jun 29 06:13:31 +0000 2026",
          "twitterUrl": "https://twitter.com/jup_lend/status/2071477143968907585",
          "likeCount": 84,
          "bookmarkCount": 4,
          "retweetCount": 9,
          "replyCount": 11,
          "viewCount": 6466,
          "thumbnailUrl": "https://pbs.twimg.com/media/HL9XI4dW4AAr6PG.jpg"
        },
        {
          "id": "2070689749581660519",
          "fullText": "Jupiter Lend makes earning simple.\n\nSwap to JUICED to start earning 5.7% APY on your JupUSD.\n\nOr take it further by looping JUICED against USDT for up to 15.5%.\n\nAnd by using our strategy vaults, you can enter into a Max Leverage Position in just 1 click. https://t.co/g0vCqoR5ya",
          "createdAt": "Sat Jun 27 02:04:42 +0000 2026",
          "twitterUrl": "https://twitter.com/jup_lend/status/2070689749581660519",
          "likeCount": 82,
          "bookmarkCount": 6,
          "retweetCount": 10,
          "replyCount": 7,
          "viewCount": 9330,
          "thumbnailUrl": "https://pbs.twimg.com/media/HLyB9dTaoAAzMFH.jpg"
        },
        {
          "id": "2069980539843711135",
          "fullText": "Tokenized stocks are hitting historic volumes on Solana\n\nAnd the best place for them is still Jupiter Lend.\n\nDeposit your xStocks to:\n\n✅ Earn xPoints (faster than holding)\n✅ Earn up to a 2% Rewards APY\n✅ Borrow stables at the lowest rate on the platform \n✅ Borrow with a 10% https://t.co/rd0Gnl6n5y",
          "createdAt": "Thu Jun 25 03:06:33 +0000 2026",
          "twitterUrl": "https://twitter.com/jup_lend/status/2069980539843711135",
          "likeCount": 74,
          "bookmarkCount": 4,
          "retweetCount": 13,
          "replyCount": 9,
          "viewCount": 7745,
          "thumbnailUrl": "https://pbs.twimg.com/media/HLoB2Kfa0AEjbZ0.jpg"
        }
      ]
    },
    {
      "twitterHandle": "sparkdotfi",
      "displayName": "Spark",
      "defiLlamaSlug": "sparklend",
      "profilePicture": "https://pbs.twimg.com/profile_images/1856332015341084672/lF5ZZXRm_normal.jpg",
      "tvl": 5123956045.17377,
      "tvlHistory": [
        {
          "date": 1780185600,
          "tvl": 3627185768
        },
        {
          "date": 1780272000,
          "tvl": 3606057862
        },
        {
          "date": 1780358400,
          "tvl": 3519130467
        },
        {
          "date": 1780444800,
          "tvl": 3434477020
        },
        {
          "date": 1780531200,
          "tvl": 3554486560
        },
        {
          "date": 1780617600,
          "tvl": 3371203104
        },
        {
          "date": 1780704000,
          "tvl": 3041305890
        },
        {
          "date": 1780790400,
          "tvl": 3130027025
        },
        {
          "date": 1780876800,
          "tvl": 3389217028
        },
        {
          "date": 1780963200,
          "tvl": 3358703834
        },
        {
          "date": 1781049600,
          "tvl": 3334821436
        },
        {
          "date": 1781136000,
          "tvl": 3268596639
        },
        {
          "date": 1781222400,
          "tvl": 3366285237
        },
        {
          "date": 1781308800,
          "tvl": 3341338411
        },
        {
          "date": 1781395200,
          "tvl": 3376565242
        },
        {
          "date": 1781481600,
          "tvl": 3429276415
        },
        {
          "date": 1781568000,
          "tvl": 3474120311
        },
        {
          "date": 1781654400,
          "tvl": 3479853397
        },
        {
          "date": 1781740800,
          "tvl": 3434535691
        },
        {
          "date": 1781827200,
          "tvl": 3373298602
        },
        {
          "date": 1781913600,
          "tvl": 3367592454
        },
        {
          "date": 1782000000,
          "tvl": 3474454691
        },
        {
          "date": 1782086400,
          "tvl": 3440925218
        },
        {
          "date": 1782172800,
          "tvl": 3506858547
        },
        {
          "date": 1782259200,
          "tvl": 3350874478
        },
        {
          "date": 1782345600,
          "tvl": 3273761512
        },
        {
          "date": 1782432000,
          "tvl": 3332372872
        },
        {
          "date": 1782518400,
          "tvl": 3431011500
        },
        {
          "date": 1782604800,
          "tvl": 3414807590
        },
        {
          "date": 1782691200,
          "tvl": 3404664576
        },
        {
          "date": 1782733043,
          "tvl": 3419134430
        }
      ],
      "aiSummary": "",
      "tweets": [
        {
          "id": "2071557936451596521",
          "fullText": "https://t.co/vwY1ai8VaC",
          "createdAt": "Mon Jun 29 11:34:34 +0000 2026",
          "twitterUrl": "https://twitter.com/sparkdotfi/status/2071557936451596521",
          "likeCount": 35,
          "bookmarkCount": 2,
          "retweetCount": 3,
          "replyCount": 6,
          "viewCount": 2780
        },
        {
          "id": "2069782234240848122",
          "fullText": "AMA tomorrow with @BinanceWallet and Sarah Grace (@inkavod) Spark's Head of Growth. \n\nJune 25th, 2026, 1 PM UTC👇",
          "createdAt": "Wed Jun 24 13:58:33 +0000 2026",
          "twitterUrl": "https://twitter.com/sparkdotfi/status/2069782234240848122",
          "likeCount": 27,
          "bookmarkCount": 0,
          "retweetCount": 6,
          "replyCount": 10,
          "viewCount": 4885
        },
        {
          "id": "2069409634117705737",
          "fullText": "Following last week's SPK unlock, the ecosystem continues to show signs of protocol health and alignment.\n\nTotal staked SPK increased from 551M to 616.3M after the unlock, while Spark's treasury continued its SPK buyback program on a regular cadence.\n\nTopline:\nProjected Yearly https://t.co/I3QQMJ00Vv",
          "createdAt": "Tue Jun 23 13:17:59 +0000 2026",
          "twitterUrl": "https://twitter.com/sparkdotfi/status/2069409634117705737",
          "likeCount": 44,
          "bookmarkCount": 5,
          "retweetCount": 12,
          "replyCount": 12,
          "viewCount": 23304,
          "thumbnailUrl": "https://pbs.twimg.com/media/HLgFGCDaYAAuYZx.jpg"
        },
        {
          "id": "2069376023481757719",
          "fullText": "Live now.",
          "createdAt": "Tue Jun 23 11:04:25 +0000 2026",
          "twitterUrl": "https://twitter.com/sparkdotfi/status/2069376023481757719",
          "likeCount": 9,
          "bookmarkCount": 0,
          "retweetCount": 2,
          "replyCount": 2,
          "viewCount": 4436
        },
        {
          "id": "2069054540523909443",
          "fullText": "Don't miss it: Tune in and listen to @MonetSupply (Head of Strategy) on how Spark approaches risk, and planning for the known and the unknown.\n\nHappening tomorrow.\nJune 23, 2026, 11 AM – 12 PM UTC | 7 – 8 PM GMT+8\n👇",
          "createdAt": "Mon Jun 22 13:46:58 +0000 2026",
          "twitterUrl": "https://twitter.com/sparkdotfi/status/2069054540523909443",
          "likeCount": 24,
          "bookmarkCount": 1,
          "retweetCount": 8,
          "replyCount": 3,
          "viewCount": 5266
        }
      ]
    },
    {
      "twitterHandle": "loopscale",
      "displayName": "Loopscale",
      "defiLlamaSlug": "loopscale",
      "profilePicture": "https://pbs.twimg.com/profile_images/1896677394506784768/f_moNZvF_normal.png",
      "tvl": 79178356.59137,
      "tvlHistory": [
        {
          "date": 1780185600,
          "tvl": 81835159
        },
        {
          "date": 1780272000,
          "tvl": 81482763
        },
        {
          "date": 1780358400,
          "tvl": 75671877
        },
        {
          "date": 1780444800,
          "tvl": 72313995
        },
        {
          "date": 1780531200,
          "tvl": 72370401
        },
        {
          "date": 1780617600,
          "tvl": 66521659
        },
        {
          "date": 1780704000,
          "tvl": 65545233
        },
        {
          "date": 1780790400,
          "tvl": 64131373
        },
        {
          "date": 1780876800,
          "tvl": 66815843
        },
        {
          "date": 1780963200,
          "tvl": 73909478
        },
        {
          "date": 1781049600,
          "tvl": 73803354
        },
        {
          "date": 1781136000,
          "tvl": 72053022
        },
        {
          "date": 1781222400,
          "tvl": 74164817
        },
        {
          "date": 1781308800,
          "tvl": 74895532
        },
        {
          "date": 1781395200,
          "tvl": 75620991
        },
        {
          "date": 1781481600,
          "tvl": 77647398
        },
        {
          "date": 1781568000,
          "tvl": 78524328
        },
        {
          "date": 1781654400,
          "tvl": 80366790
        },
        {
          "date": 1781740800,
          "tvl": 80160323
        },
        {
          "date": 1781827200,
          "tvl": 79370149
        },
        {
          "date": 1781913600,
          "tvl": 79317590
        },
        {
          "date": 1782000000,
          "tvl": 79251437
        },
        {
          "date": 1782086400,
          "tvl": 79373434
        },
        {
          "date": 1782172800,
          "tvl": 79178356
        }
      ],
      "aiSummary": "",
      "tweets": [
        {
          "id": "2068031135729500652",
          "fullText": "Loopscale + @Collector_Crypt\n\nSubmit your collectibles today and borrow fixed-rate USDC against your collection.\n\n→ https://t.co/bqpuH4eg2u https://t.co/XzhFrqSDZp",
          "createdAt": "Fri Jun 19 18:00:19 +0000 2026",
          "twitterUrl": "https://twitter.com/Loopscale/status/2068031135729500652",
          "likeCount": 87,
          "bookmarkCount": 6,
          "retweetCount": 19,
          "replyCount": 9,
          "viewCount": 8149,
          "thumbnailUrl": "https://pbs.twimg.com/amplify_video_thumb/2068031085112614913/img/YkZejOFN9pGHh09W.jpg"
        },
        {
          "id": "2070573524553437480",
          "fullText": "A graded Crystal Lugia, collateralized for a fixed-rate USDC loan.\n\nBorrow against your collectibles on Loopscale.",
          "createdAt": "Fri Jun 26 18:22:52 +0000 2026",
          "twitterUrl": "https://twitter.com/Loopscale/status/2070573524553437480",
          "likeCount": 13,
          "bookmarkCount": 1,
          "retweetCount": 1,
          "replyCount": 3,
          "viewCount": 2959
        },
        {
          "id": "2070152738235949555",
          "fullText": "Introducing Loop Vaults on Loopscale Earn, starting with @humafinance's PST.\n\nDeposit once and earn maximized yield across PST loops on Loopscale, @kamino, and @jup_lend. No active management required.\n\nOnly possible on Loopscale. https://t.co/Oik4vzUz1W",
          "createdAt": "Thu Jun 25 14:30:49 +0000 2026",
          "twitterUrl": "https://twitter.com/Loopscale/status/2070152738235949555",
          "likeCount": 55,
          "bookmarkCount": 6,
          "retweetCount": 5,
          "replyCount": 15,
          "viewCount": 15261,
          "thumbnailUrl": "https://pbs.twimg.com/amplify_video_thumb/2070152686067163136/img/uGqfnLTVKoZSa58t.jpg"
        },
        {
          "id": "2067698930788581816",
          "fullText": "SOL Main is now live on Loopscale Earn.\n\nDeposit SOL and earn a higher yield than staking or lending in one position, with instant withdrawals and lower fees than unstaking an LST. Rebalanced daily across SOL yield sources:\n\n• SOL lent into markets on Loopscale and @kamino\n• A https://t.co/TEEiDkoEXw",
          "createdAt": "Thu Jun 18 20:00:15 +0000 2026",
          "twitterUrl": "https://twitter.com/Loopscale/status/2067698930788581816",
          "likeCount": 102,
          "bookmarkCount": 7,
          "retweetCount": 10,
          "replyCount": 20,
          "viewCount": 9610,
          "thumbnailUrl": "https://pbs.twimg.com/amplify_video_thumb/2067698878774927360/img/vQncP3ZtWTNltbUr.jpg"
        },
        {
          "id": "2067351635047989621",
          "fullText": "Loopscale's biggest portfolio upgrade yet is live.\n\nManage multiple positions in one click:\n\n• Merge loans into a single position at the lowest APY\n• Bulk deposit and withdraw across Lend Vault and Advanced Lend\n• Track positions in a new grouped view, aggregated by market https://t.co/7jz2hSoZsW",
          "createdAt": "Wed Jun 17 21:00:13 +0000 2026",
          "twitterUrl": "https://twitter.com/Loopscale/status/2067351635047989621",
          "likeCount": 56,
          "bookmarkCount": 2,
          "retweetCount": 3,
          "replyCount": 11,
          "viewCount": 2505,
          "thumbnailUrl": "https://pbs.twimg.com/amplify_video_thumb/2067351583386685440/img/nkm-xcSHYq6usJBm.jpg"
        }
      ]
    },
    {
      "twitterHandle": "morpho",
      "displayName": "Morpho 🦋",
      "defiLlamaSlug": "morpho-v1",
      "profilePicture": "https://pbs.twimg.com/profile_images/1930600293915410432/dgTU7UNU_normal.jpg",
      "tvl": 10231456488.6402,
      "tvlHistory": [
        {
          "date": 1780185600,
          "tvl": 7324984606
        },
        {
          "date": 1780272000,
          "tvl": 7321893789
        },
        {
          "date": 1780358400,
          "tvl": 7219417979
        },
        {
          "date": 1780444800,
          "tvl": 6834141676
        },
        {
          "date": 1780531200,
          "tvl": 6713128524
        },
        {
          "date": 1780617600,
          "tvl": 6606323356
        },
        {
          "date": 1780704000,
          "tvl": 6345434332
        },
        {
          "date": 1780790400,
          "tvl": 6315237011
        },
        {
          "date": 1780876800,
          "tvl": 6660378714
        },
        {
          "date": 1780963200,
          "tvl": 6517757056
        },
        {
          "date": 1781049600,
          "tvl": 6373993884
        },
        {
          "date": 1781136000,
          "tvl": 6346113802
        },
        {
          "date": 1781222400,
          "tvl": 6552907941
        },
        {
          "date": 1781308800,
          "tvl": 6633167281
        },
        {
          "date": 1781395200,
          "tvl": 6736614073
        },
        {
          "date": 1781481600,
          "tvl": 6867740598
        },
        {
          "date": 1781568000,
          "tvl": 7016124515
        },
        {
          "date": 1781654400,
          "tvl": 7150072199
        },
        {
          "date": 1781740800,
          "tvl": 7023494782
        },
        {
          "date": 1781827200,
          "tvl": 6871585659
        },
        {
          "date": 1781913600,
          "tvl": 6931455341
        },
        {
          "date": 1782000000,
          "tvl": 6900402723
        },
        {
          "date": 1782086400,
          "tvl": 6820768820
        },
        {
          "date": 1782172800,
          "tvl": 6854587234
        },
        {
          "date": 1782259200,
          "tvl": 6765553600
        },
        {
          "date": 1782345600,
          "tvl": 6652287091
        },
        {
          "date": 1782432000,
          "tvl": 6513492470
        },
        {
          "date": 1782518400,
          "tvl": 6557238327
        },
        {
          "date": 1782604800,
          "tvl": 6547927315
        },
        {
          "date": 1782691200,
          "tvl": 6556024161
        },
        {
          "date": 1782734147,
          "tvl": 6592470637
        }
      ],
      "aiSummary": "",
      "tweets": [
        {
          "id": "2070141977371586863",
          "fullText": "Access Morpho-powered yield via @elwood_io\n\nInstitutional users of Elwood’s Portfolio Management System can allocate to Morpho Vaults curated by @steakhousefi &amp; @gauntlet_xyz, without having to change their workflow or compliance processes. https://t.co/hy2w8c3uqU",
          "createdAt": "Thu Jun 25 13:48:03 +0000 2026",
          "twitterUrl": "https://twitter.com/Morpho/status/2070141977371586863",
          "likeCount": 50,
          "bookmarkCount": 4,
          "retweetCount": 6,
          "replyCount": 8,
          "viewCount": 6806,
          "thumbnailUrl": "https://pbs.twimg.com/media/HLqfKDIagAAPK8P.jpg"
        },
        {
          "id": "2069109818506584124",
          "fullText": "Morpho will soon be accessible on @BitGo\n\nBitGo is a leading custodian with over $100B in assets and 5500 institutional clients.\n\nBitgo clients can earn rewards on idle assets via curated Morpho Vaults, all within the security of Bitgo custody. https://t.co/Uouh1omxVu",
          "createdAt": "Mon Jun 22 17:26:37 +0000 2026",
          "twitterUrl": "https://twitter.com/Morpho/status/2069109818506584124",
          "likeCount": 143,
          "bookmarkCount": 9,
          "retweetCount": 15,
          "replyCount": 15,
          "viewCount": 30103,
          "thumbnailUrl": "https://pbs.twimg.com/amplify_video_thumb/2069109767621283840/img/l1bArCic51bcJZeH.jpg"
        },
        {
          "id": "2067189345195610548",
          "fullText": "Deposit Confidential Tokens with @zama on Morpho\n\nInstitutional allocators, corporate treasuries and market participants can earn yield from @SteakhouseFi curated Morpho Vaults without disclosing their balances or strategies https://t.co/RTAncrPXR1",
          "createdAt": "Wed Jun 17 10:15:21 +0000 2026",
          "twitterUrl": "https://twitter.com/Morpho/status/2067189345195610548",
          "likeCount": 215,
          "bookmarkCount": 29,
          "retweetCount": 28,
          "replyCount": 55,
          "viewCount": 68589,
          "thumbnailUrl": "https://pbs.twimg.com/amplify_video_thumb/2067189294255722496/img/jpDqixvDy7gsDHni.jpg"
        },
        {
          "id": "2066937641975869666",
          "fullText": "First of its kind: @buildwithjuno by @bitso just launched Mexican Peso onchain credit markets and vaults on Morpho, curated by @gauntlet_xyz.\n\nThe blueprint for LATAM stablecoin onchain utility - users can access $MXNB liquidity against $USDC &amp; $BTC, or put $MXNB to work on https://t.co/GsV4NjGRkw",
          "createdAt": "Tue Jun 16 17:35:10 +0000 2026",
          "twitterUrl": "https://twitter.com/Morpho/status/2066937641975869666",
          "likeCount": 151,
          "bookmarkCount": 11,
          "retweetCount": 21,
          "replyCount": 36,
          "viewCount": 43659,
          "thumbnailUrl": "https://pbs.twimg.com/media/HK881OQa0AAcM-P.jpg"
        },
        {
          "id": "2065151934978461954",
          "fullText": "More choices for USDC Earn on @coinbase, powered by Morpho\n\nUsers can now pick between @SteakhouseFi curated vaults with distinct risk profiles:\n\nA Prime vault backed by $BTC and $ETH, and a High Yield vault backed by @ethena assets and more. https://t.co/UFTWSRLxuq",
          "createdAt": "Thu Jun 11 19:19:24 +0000 2026",
          "twitterUrl": "https://twitter.com/Morpho/status/2065151934978461954",
          "likeCount": 223,
          "bookmarkCount": 33,
          "retweetCount": 27,
          "replyCount": 39,
          "viewCount": 53694,
          "thumbnailUrl": "https://pbs.twimg.com/amplify_video_thumb/2065151882872627200/img/Tn8nAcT-9Brv0gvW.jpg"
        }
      ]
    },
    {
      "twitterHandle": "yearnfi",
      "displayName": "yearn",
      "defiLlamaSlug": "yearn-finance",
      "profilePicture": "https://pbs.twimg.com/profile_images/2056457364337807360/jVobxTcg_normal.png",
      "tvl": 140606912.97427002,
      "tvlHistory": [
        {
          "date": 1780185600,
          "tvl": 170900865
        },
        {
          "date": 1780272000,
          "tvl": 170616139
        },
        {
          "date": 1780358400,
          "tvl": 169797428
        },
        {
          "date": 1780444800,
          "tvl": 169725265
        },
        {
          "date": 1780531200,
          "tvl": 166166639
        },
        {
          "date": 1780617600,
          "tvl": 173810023
        },
        {
          "date": 1780704000,
          "tvl": 158227108
        },
        {
          "date": 1780790400,
          "tvl": 155343145
        },
        {
          "date": 1780876800,
          "tvl": 153895973
        },
        {
          "date": 1780963200,
          "tvl": 153649806
        },
        {
          "date": 1781049600,
          "tvl": 151905297
        },
        {
          "date": 1781136000,
          "tvl": 151530592
        },
        {
          "date": 1781222400,
          "tvl": 153727207
        },
        {
          "date": 1781308800,
          "tvl": 151578735
        },
        {
          "date": 1781395200,
          "tvl": 152000126
        },
        {
          "date": 1781481600,
          "tvl": 149492936
        },
        {
          "date": 1781568000,
          "tvl": 151787770
        },
        {
          "date": 1781654400,
          "tvl": 151447226
        },
        {
          "date": 1781740800,
          "tvl": 150061187
        },
        {
          "date": 1781827200,
          "tvl": 146461689
        },
        {
          "date": 1781913600,
          "tvl": 146049198
        },
        {
          "date": 1782000000,
          "tvl": 147842103
        },
        {
          "date": 1782086400,
          "tvl": 146589548
        },
        {
          "date": 1782172800,
          "tvl": 146965305
        },
        {
          "date": 1782259200,
          "tvl": 144553732
        },
        {
          "date": 1782345600,
          "tvl": 142932498
        },
        {
          "date": 1782432000,
          "tvl": 140437516
        },
        {
          "date": 1782518400,
          "tvl": 141023333
        },
        {
          "date": 1782604800,
          "tvl": 140474500
        },
        {
          "date": 1782691200,
          "tvl": 140486441
        },
        {
          "date": 1782733223,
          "tvl": 140606912
        }
      ],
      "aiSummary": "",
      "tweets": [
        {
          "id": "2070188562222367085",
          "fullText": "👀",
          "createdAt": "Thu Jun 25 16:53:10 +0000 2026",
          "twitterUrl": "https://twitter.com/yearnfi/status/2070188562222367085",
          "likeCount": 13,
          "bookmarkCount": 0,
          "retweetCount": 2,
          "replyCount": 1,
          "viewCount": 6853
        },
        {
          "id": "2070160584457191835",
          "fullText": "https://t.co/WAuI7pNl0Y",
          "createdAt": "Thu Jun 25 15:01:59 +0000 2026",
          "twitterUrl": "https://twitter.com/yearnfi/status/2070160584457191835",
          "likeCount": 15,
          "bookmarkCount": 1,
          "retweetCount": 1,
          "replyCount": 1,
          "viewCount": 3459
        },
        {
          "id": "2067607339222372369",
          "fullText": "https://t.co/lhZv16uy4A",
          "createdAt": "Thu Jun 18 13:56:18 +0000 2026",
          "twitterUrl": "https://twitter.com/yearnfi/status/2067607339222372369",
          "likeCount": 14,
          "bookmarkCount": 3,
          "retweetCount": 4,
          "replyCount": 2,
          "viewCount": 1655
        },
        {
          "id": "2066553675880022365",
          "fullText": "Earn auto-compounded BOLD and boosted CRV rewards, plus airdrops from 15+ Liquity forks. What more could you want?",
          "createdAt": "Mon Jun 15 16:09:25 +0000 2026",
          "twitterUrl": "https://twitter.com/yearnfi/status/2066553675880022365",
          "likeCount": 20,
          "bookmarkCount": 1,
          "retweetCount": 5,
          "replyCount": 3,
          "viewCount": 2455
        },
        {
          "id": "2065094152350560259",
          "fullText": "👀",
          "createdAt": "Thu Jun 11 15:29:48 +0000 2026",
          "twitterUrl": "https://twitter.com/yearnfi/status/2065094152350560259",
          "likeCount": 18,
          "bookmarkCount": 0,
          "retweetCount": 4,
          "replyCount": 1,
          "viewCount": 1850
        }
      ]
    },
    {
      "twitterHandle": "eulerfinance",
      "displayName": "Euler Labs",
      "defiLlamaSlug": "euler-v2",
      "profilePicture": "https://pbs.twimg.com/profile_images/1947602115557527553/15Jr7cIa_normal.jpg",
      "tvl": 931268168.95396,
      "tvlHistory": [
        {
          "date": 1780185600,
          "tvl": 283680301
        },
        {
          "date": 1780272000,
          "tvl": 286231793
        },
        {
          "date": 1780358400,
          "tvl": 286437288
        },
        {
          "date": 1780444800,
          "tvl": 267637428
        },
        {
          "date": 1780531200,
          "tvl": 270093497
        },
        {
          "date": 1780617600,
          "tvl": 265616702
        },
        {
          "date": 1780704000,
          "tvl": 257431595
        },
        {
          "date": 1780790400,
          "tvl": 258986961
        },
        {
          "date": 1780876800,
          "tvl": 283124074
        },
        {
          "date": 1780963200,
          "tvl": 272523447
        },
        {
          "date": 1781049600,
          "tvl": 265023132
        },
        {
          "date": 1781136000,
          "tvl": 272915981
        },
        {
          "date": 1781222400,
          "tvl": 280680852
        },
        {
          "date": 1781308800,
          "tvl": 264316976
        },
        {
          "date": 1781395200,
          "tvl": 285746026
        },
        {
          "date": 1781481600,
          "tvl": 286885180
        },
        {
          "date": 1781568000,
          "tvl": 272684452
        },
        {
          "date": 1781654400,
          "tvl": 270528878
        },
        {
          "date": 1781740800,
          "tvl": 266596862
        },
        {
          "date": 1781827200,
          "tvl": 268426659
        },
        {
          "date": 1781913600,
          "tvl": 282013410
        },
        {
          "date": 1782000000,
          "tvl": 277062410
        },
        {
          "date": 1782086400,
          "tvl": 271424476
        },
        {
          "date": 1782172800,
          "tvl": 283403697
        },
        {
          "date": 1782259200,
          "tvl": 272285272
        },
        {
          "date": 1782345600,
          "tvl": 272688673
        },
        {
          "date": 1782432000,
          "tvl": 290775360
        },
        {
          "date": 1782518400,
          "tvl": 292069720
        },
        {
          "date": 1782604800,
          "tvl": 283146352
        },
        {
          "date": 1782691200,
          "tvl": 285768434
        },
        {
          "date": 1782732983,
          "tvl": 277030381
        }
      ],
      "aiSummary": "",
      "tweets": [
        {
          "id": "2070525491011109062",
          "fullText": "Euler gives each address up to 256 sub-accounts.\n\nOne wallet can separate positions, collateral relationships, and strategies.\n\nFor users and agents, each position becomes easier to read, manage, and reason about without mixing everything into one account. https://t.co/RXDRCAw1Sd",
          "createdAt": "Fri Jun 26 15:12:00 +0000 2026",
          "twitterUrl": "https://twitter.com/eulerfinance/status/2070525491011109062",
          "likeCount": 64,
          "bookmarkCount": 5,
          "retweetCount": 4,
          "replyCount": 5,
          "viewCount": 4699,
          "thumbnailUrl": "https://pbs.twimg.com/amplify_video_thumb/2070480902744846336/img/Mn77KNCm_-UWGx93.jpg"
        },
        {
          "id": "2070163773529182276",
          "fullText": "Euler turns lending market design into a configurable system.\n\nEach vault can define its underlying asset, accepted collateral, oracle, caps, liquidation parameters, and interest-rate model.\n\nLending markets shaped around specific assets and risk parameters, not a https://t.co/uOj7BouMM8",
          "createdAt": "Thu Jun 25 15:14:40 +0000 2026",
          "twitterUrl": "https://twitter.com/eulerfinance/status/2070163773529182276",
          "likeCount": 38,
          "bookmarkCount": 5,
          "retweetCount": 2,
          "replyCount": 5,
          "viewCount": 3419,
          "thumbnailUrl": "https://pbs.twimg.com/amplify_video_thumb/2070163175975088128/img/_O4205ew-6hb9KCA.jpg"
        },
        {
          "id": "2067629369724641419",
          "fullText": "Borrow activity on @base is up 5.6x in 30 days.\n\nIn the same window, supplied assets across Base vaults grew by $21.9m. https://t.co/LUxoiPYc63",
          "createdAt": "Thu Jun 18 15:23:51 +0000 2026",
          "twitterUrl": "https://twitter.com/eulerfinance/status/2067629369724641419",
          "likeCount": 44,
          "bookmarkCount": 1,
          "retweetCount": 6,
          "replyCount": 3,
          "viewCount": 3494,
          "thumbnailUrl": "https://pbs.twimg.com/media/HLGx9F_bMAA7Ex9.jpg"
        },
        {
          "id": "2067247964758704188",
          "fullText": "Swellchain is sunsetting.\n\nEUL holders with positions on Swellchain should withdraw before the June 23 deadline. Funds remaining after that date may be unrecoverable.",
          "createdAt": "Wed Jun 17 14:08:17 +0000 2026",
          "twitterUrl": "https://twitter.com/eulerfinance/status/2067247964758704188",
          "likeCount": 28,
          "bookmarkCount": 2,
          "retweetCount": 2,
          "replyCount": 5,
          "viewCount": 3946
        },
        {
          "id": "2065464255931887672",
          "fullText": "For institutions, public wallet activity can expose strategy, position size, and rebalancing decisions.\n\nUnlink brings a privacy layer to Euler vault transactions, reducing the public link between an institution’s wallet and how it uses onchain credit markets.",
          "createdAt": "Fri Jun 12 16:00:27 +0000 2026",
          "twitterUrl": "https://twitter.com/eulerfinance/status/2065464255931887672",
          "likeCount": 59,
          "bookmarkCount": 3,
          "retweetCount": 7,
          "replyCount": 5,
          "viewCount": 4864
        }
      ]
    },
    {
      "twitterHandle": "venusprotocol",
      "displayName": "Venus Protocol",
      "defiLlamaSlug": "venus-core-pool",
      "profilePicture": "https://pbs.twimg.com/profile_images/1942208446868185088/YbdsNx5f_normal.jpg",
      "tvl": 1360104754.9222999,
      "tvlHistory": [
        {
          "date": 1780185600,
          "tvl": 1184664904
        },
        {
          "date": 1780272000,
          "tvl": 1177345766
        },
        {
          "date": 1780358400,
          "tvl": 1144321124
        },
        {
          "date": 1780444800,
          "tvl": 1084792935
        },
        {
          "date": 1780531200,
          "tvl": 1048923498
        },
        {
          "date": 1780617600,
          "tvl": 1041867421
        },
        {
          "date": 1780704000,
          "tvl": 989986608
        },
        {
          "date": 1780790400,
          "tvl": 993606137
        },
        {
          "date": 1780876800,
          "tvl": 1029252465
        },
        {
          "date": 1780963200,
          "tvl": 1021512755
        },
        {
          "date": 1781049600,
          "tvl": 1011760208
        },
        {
          "date": 1781136000,
          "tvl": 1024408816
        },
        {
          "date": 1781222400,
          "tvl": 1051014989
        },
        {
          "date": 1781308800,
          "tvl": 1057868693
        },
        {
          "date": 1781395200,
          "tvl": 1058919514
        },
        {
          "date": 1781481600,
          "tvl": 1071520186
        },
        {
          "date": 1781568000,
          "tvl": 1082803575
        },
        {
          "date": 1781654400,
          "tvl": 1077778710
        },
        {
          "date": 1781740800,
          "tvl": 1062051593
        },
        {
          "date": 1781827200,
          "tvl": 1032109900
        },
        {
          "date": 1781913600,
          "tvl": 1027747017
        },
        {
          "date": 1782000000,
          "tvl": 1041901691
        },
        {
          "date": 1782086400,
          "tvl": 1031621931
        },
        {
          "date": 1782172800,
          "tvl": 1048174078
        },
        {
          "date": 1782259200,
          "tvl": 1027239031
        },
        {
          "date": 1782345600,
          "tvl": 1005214726
        },
        {
          "date": 1782432000,
          "tvl": 999649848
        },
        {
          "date": 1782518400,
          "tvl": 991393056
        },
        {
          "date": 1782604800,
          "tvl": 998753402
        },
        {
          "date": 1782691200,
          "tvl": 989090914
        },
        {
          "date": 1782735515,
          "tvl": 984723688
        }
      ],
      "aiSummary": "",
      "tweets": [
        {
          "id": "2071572583720611958",
          "fullText": "Confused by bStocks on-chain? Join us as we hash it all out with @TrustWallet on 30th June, noon (UTC). \n\nBe there or be square! 🟨",
          "createdAt": "Mon Jun 29 12:32:46 +0000 2026",
          "twitterUrl": "https://twitter.com/VenusProtocol/status/2071572583720611958",
          "likeCount": 8,
          "bookmarkCount": 0,
          "retweetCount": 0,
          "replyCount": 3,
          "viewCount": 2134
        },
        {
          "id": "2071083079683477739",
          "fullText": "What can you do after collateralizing bStocks on Venus? 💭 \n\n👉🏼 Choose from any borrowable asset on Venus Core! With nearly 20 tokens to choose from, you can borrow anything that suits your needs.",
          "createdAt": "Sun Jun 28 04:07:39 +0000 2026",
          "twitterUrl": "https://twitter.com/VenusProtocol/status/2071083079683477739",
          "likeCount": 22,
          "bookmarkCount": 1,
          "retweetCount": 3,
          "replyCount": 5,
          "viewCount": 5732
        },
        {
          "id": "2070401233379299699",
          "fullText": "Final hours to grab your share of a $50,000 reward pool just by supplying USDT on Venus Flux through @BinanceWallet! Don't miss it.",
          "createdAt": "Fri Jun 26 06:58:14 +0000 2026",
          "twitterUrl": "https://twitter.com/VenusProtocol/status/2070401233379299699",
          "likeCount": 14,
          "bookmarkCount": 0,
          "retweetCount": 0,
          "replyCount": 3,
          "viewCount": 4414
        },
        {
          "id": "2069637028912963904",
          "fullText": "don’t let your holdings just be holdings!",
          "createdAt": "Wed Jun 24 04:21:34 +0000 2026",
          "twitterUrl": "https://twitter.com/VenusProtocol/status/2069637028912963904",
          "likeCount": 14,
          "bookmarkCount": 0,
          "retweetCount": 1,
          "replyCount": 2,
          "viewCount": 3944
        },
        {
          "id": "2069425882930762142",
          "fullText": "The Venus Trade Cup🏆 is still running and there's still time to climb⚽️ \n\n$2,500 prize pool. One leaderboard. Ends Jul 20.\n\nOpen a position on Venus Trade and see where you land.\n\nhttps://t.co/IiVnGNJYbO",
          "createdAt": "Tue Jun 23 14:22:33 +0000 2026",
          "twitterUrl": "https://twitter.com/VenusProtocol/status/2069425882930762142",
          "likeCount": 17,
          "bookmarkCount": 0,
          "retweetCount": 5,
          "replyCount": 0,
          "viewCount": 2887
        }
      ]
    },
    {
      "twitterHandle": "DriftProtocol",
      "displayName": "Drift",
      "defiLlamaSlug": "drift-trade",
      "profilePicture": "https://pbs.twimg.com/profile_images/1996562092879663104/5W5GGU9U_normal.png",
      "tvl": 5519234.61348,
      "tvlHistory": [
        {
          "date": 1780185600,
          "tvl": 6282366
        },
        {
          "date": 1780272000,
          "tvl": 6298915
        },
        {
          "date": 1780358400,
          "tvl": 6293830
        },
        {
          "date": 1780444800,
          "tvl": 5891516
        },
        {
          "date": 1780531200,
          "tvl": 6064944
        },
        {
          "date": 1780617600,
          "tvl": 5808530
        },
        {
          "date": 1780704000,
          "tvl": 5412917
        },
        {
          "date": 1780790400,
          "tvl": 5372382
        },
        {
          "date": 1780876800,
          "tvl": 5599459
        },
        {
          "date": 1780963200,
          "tvl": 5591950
        },
        {
          "date": 1781049600,
          "tvl": 5540033
        },
        {
          "date": 1781136000,
          "tvl": 5300048
        },
        {
          "date": 1781222400,
          "tvl": 5471864
        },
        {
          "date": 1781308800,
          "tvl": 5553830
        },
        {
          "date": 1781395200,
          "tvl": 5625746
        },
        {
          "date": 1781481600,
          "tvl": 5716525
        },
        {
          "date": 1781568000,
          "tvl": 5753067
        },
        {
          "date": 1781654400,
          "tvl": 5683999
        },
        {
          "date": 1781740800,
          "tvl": 5610616
        },
        {
          "date": 1781827200,
          "tvl": 5537488
        },
        {
          "date": 1781913600,
          "tvl": 5475746
        },
        {
          "date": 1782000000,
          "tvl": 5575606
        },
        {
          "date": 1782086400,
          "tvl": 5690750
        },
        {
          "date": 1782172800,
          "tvl": 5612704
        },
        {
          "date": 1782259200,
          "tvl": 5568483
        },
        {
          "date": 1782345600,
          "tvl": 5306388
        },
        {
          "date": 1782432000,
          "tvl": 5165691
        },
        {
          "date": 1782518400,
          "tvl": 5419238
        },
        {
          "date": 1782604800,
          "tvl": 5445714
        },
        {
          "date": 1782691200,
          "tvl": 5526611
        },
        {
          "date": 1782733835,
          "tvl": 5519234
        }
      ],
      "aiSummary": "",
      "tweets": [
        {
          "id": "2052015574809710977",
          "fullText": "Clarification: \nUsers are able to redeem at any time after redemption opens; however, early redemption occurs at a discount to the full claim value as users receive a pro-rata share of the current pool. Holders who wait may benefit from a higher recovery price as the pool",
          "createdAt": "Wed May 06 13:20:12 +0000 2026",
          "twitterUrl": "https://twitter.com/DriftProtocol/status/2052015574809710977",
          "likeCount": 95,
          "bookmarkCount": 8,
          "retweetCount": 16,
          "replyCount": 123,
          "viewCount": 41129
        },
        {
          "id": "2067654293247713304",
          "fullText": "The Recovery Token and Insurance Fund Claim Checker is now live.\n\nAffected users can now connect their wallet to view their Recovery Token allocation and Insurance Fund claim eligibility.",
          "createdAt": "Thu Jun 18 17:02:53 +0000 2026",
          "twitterUrl": "https://twitter.com/DriftProtocol/status/2067654293247713304",
          "likeCount": 197,
          "bookmarkCount": 55,
          "retweetCount": 34,
          "replyCount": 63,
          "viewCount": 48297
        },
        {
          "id": "2062341550101704763",
          "fullText": "Today we are sharing an update on Drift recovery and relaunch \n\nhttps://t.co/pn4121cUp3",
          "createdAt": "Thu Jun 04 01:11:56 +0000 2026",
          "twitterUrl": "https://twitter.com/DriftProtocol/status/2062341550101704763",
          "likeCount": 190,
          "bookmarkCount": 24,
          "retweetCount": 18,
          "replyCount": 72,
          "viewCount": 101643
        },
        {
          "id": "2057103397266854288",
          "fullText": "Update: Insurance Fund depositors will be able to withdraw their Insurance Fund stake when the protocol goes live.\n\nDrift’s documentation and code demonstrates that the Insurance Fund exists to maintain protocol solvency in the event of bankruptcies.\n\nGiven that the protocol was",
          "createdAt": "Wed May 20 14:17:23 +0000 2026",
          "twitterUrl": "https://twitter.com/DriftProtocol/status/2057103397266854288",
          "likeCount": 149,
          "bookmarkCount": 14,
          "retweetCount": 16,
          "replyCount": 62,
          "viewCount": 56087
        },
        {
          "id": "2051666099675025732",
          "fullText": "We told our community we would find a path to recovery. This is that path.\n\nToday’s update covers: how users will be compensated and how the exchange is being rebuilt.",
          "createdAt": "Tue May 05 14:11:30 +0000 2026",
          "twitterUrl": "https://twitter.com/DriftProtocol/status/2051666099675025732",
          "likeCount": 351,
          "bookmarkCount": 60,
          "retweetCount": 47,
          "replyCount": 150,
          "viewCount": 125088
        }
      ]
    },
    {
      "twitterHandle": "deficarrot",
      "displayName": "Carrot",
      "defiLlamaSlug": "carrot-lend",
      "profilePicture": "https://pbs.twimg.com/profile_images/1996652426724585473/4OvTPWz1_normal.jpg",
      "tvl": 67166.34523,
      "tvlHistory": [
        {
          "date": 1780185600,
          "tvl": 72892
        },
        {
          "date": 1780272000,
          "tvl": 72662
        },
        {
          "date": 1780358400,
          "tvl": 72969
        },
        {
          "date": 1780444800,
          "tvl": 71811
        },
        {
          "date": 1780531200,
          "tvl": 71330
        },
        {
          "date": 1780617600,
          "tvl": 71201
        },
        {
          "date": 1780704000,
          "tvl": 70616
        },
        {
          "date": 1780790400,
          "tvl": 70660
        },
        {
          "date": 1780876800,
          "tvl": 71032
        },
        {
          "date": 1780963200,
          "tvl": 67922
        },
        {
          "date": 1781049600,
          "tvl": 67755
        },
        {
          "date": 1781136000,
          "tvl": 67770
        },
        {
          "date": 1781222400,
          "tvl": 68570
        },
        {
          "date": 1781308800,
          "tvl": 68594
        },
        {
          "date": 1781395200,
          "tvl": 68277
        },
        {
          "date": 1781481600,
          "tvl": 68535
        },
        {
          "date": 1781568000,
          "tvl": 68768
        },
        {
          "date": 1781654400,
          "tvl": 68799
        },
        {
          "date": 1781740800,
          "tvl": 68623
        },
        {
          "date": 1781827200,
          "tvl": 67998
        },
        {
          "date": 1781913600,
          "tvl": 67973
        },
        {
          "date": 1782000000,
          "tvl": 67751
        },
        {
          "date": 1782086400,
          "tvl": 68249
        },
        {
          "date": 1782172800,
          "tvl": 68163
        },
        {
          "date": 1782259200,
          "tvl": 67967
        },
        {
          "date": 1782345600,
          "tvl": 67179
        },
        {
          "date": 1782432000,
          "tvl": 67068
        },
        {
          "date": 1782518400,
          "tvl": 65564
        },
        {
          "date": 1782604800,
          "tvl": 67399
        },
        {
          "date": 1782691200,
          "tvl": 67010
        },
        {
          "date": 1782728339,
          "tvl": 67166
        }
      ],
      "aiSummary": "",
      "tweets": [
        {
          "id": "2043751124046381514",
          "fullText": "Correction on this. The final drawdown from Project0 was 2.6% and the final estimated redemption price is $57.5209\n\nApologies for the error",
          "createdAt": "Mon Apr 13 18:00:13 +0000 2026",
          "twitterUrl": "https://twitter.com/DeFiCarrot/status/2043751124046381514",
          "likeCount": 17,
          "bookmarkCount": 1,
          "retweetCount": 0,
          "replyCount": 3,
          "viewCount": 5175
        },
        {
          "id": "2049907092664762624",
          "fullText": "1/ Carrot is shutting down\n\nThis is certainly not the outcome we wanted, but the situation with the Drift exploit, has proven to be catastrophic for our continued operations.",
          "createdAt": "Thu Apr 30 17:41:50 +0000 2026",
          "twitterUrl": "https://twitter.com/DeFiCarrot/status/2049907092664762624",
          "likeCount": 826,
          "bookmarkCount": 119,
          "retweetCount": 94,
          "replyCount": 279,
          "viewCount": 194461
        },
        {
          "id": "2044486486284804100",
          "fullText": "1/ We have unpaused the Carrot program. Mint/redeem is now open again. \n\nhttps://t.co/rD42OvtA7t",
          "createdAt": "Wed Apr 15 18:42:17 +0000 2026",
          "twitterUrl": "https://twitter.com/DeFiCarrot/status/2044486486284804100",
          "likeCount": 53,
          "bookmarkCount": 4,
          "retweetCount": 4,
          "replyCount": 6,
          "viewCount": 9069
        },
        {
          "id": "2043725930644861435",
          "fullText": "1/ Update on Carrot\n\nEven though we are still waiting on Drift for the official next steps from them, we are now ~90% liquid for the remaining TVL and will soon (hopefully tomorrow) open up CRT redemption.",
          "createdAt": "Mon Apr 13 16:20:07 +0000 2026",
          "twitterUrl": "https://twitter.com/DeFiCarrot/status/2043725930644861435",
          "likeCount": 87,
          "bookmarkCount": 4,
          "retweetCount": 3,
          "replyCount": 9,
          "viewCount": 10575
        },
        {
          "id": "2041599719407824968",
          "fullText": "1/ Update on Carrot\n\nWe haven't sent an update in a few days, and wanted to stay in touch even though no new official information has come from Drift yet.\n\nPlease see our discord for the full update",
          "createdAt": "Tue Apr 07 19:31:18 +0000 2026",
          "twitterUrl": "https://twitter.com/DeFiCarrot/status/2041599719407824968",
          "likeCount": 72,
          "bookmarkCount": 5,
          "retweetCount": 4,
          "replyCount": 10,
          "viewCount": 11195
        }
      ]
    },
    {
      "twitterHandle": "lista_dao",
      "displayName": "Lista DAO",
      "defiLlamaSlug": "lista-lending",
      "profilePicture": "https://pbs.twimg.com/profile_images/2006524473323778048/ekWFvFN3_normal.jpg",
      "tvl": 731766415.63747,
      "tvlHistory": [
        {
          "date": 1780185600,
          "tvl": 669738082
        },
        {
          "date": 1780272000,
          "tvl": 652798210
        },
        {
          "date": 1780358400,
          "tvl": 633627715
        },
        {
          "date": 1780444800,
          "tvl": 607031682
        },
        {
          "date": 1780531200,
          "tvl": 581820349
        },
        {
          "date": 1780617600,
          "tvl": 621810982
        },
        {
          "date": 1780704000,
          "tvl": 598228122
        },
        {
          "date": 1780790400,
          "tvl": 600002956
        },
        {
          "date": 1780876800,
          "tvl": 623779558
        },
        {
          "date": 1780963200,
          "tvl": 619456419
        },
        {
          "date": 1781049600,
          "tvl": 612541059
        },
        {
          "date": 1781136000,
          "tvl": 608665284
        },
        {
          "date": 1781222400,
          "tvl": 631505261
        },
        {
          "date": 1781308800,
          "tvl": 639491607
        },
        {
          "date": 1781395200,
          "tvl": 650612291
        },
        {
          "date": 1781481600,
          "tvl": 652330514
        },
        {
          "date": 1781568000,
          "tvl": 658851719
        },
        {
          "date": 1781654400,
          "tvl": 650380100
        },
        {
          "date": 1781740800,
          "tvl": 638764970
        },
        {
          "date": 1781827200,
          "tvl": 603304468
        },
        {
          "date": 1781913600,
          "tvl": 619156144
        },
        {
          "date": 1782000000,
          "tvl": 631361764
        },
        {
          "date": 1782086400,
          "tvl": 632260711
        },
        {
          "date": 1782172800,
          "tvl": 643108783
        },
        {
          "date": 1782259200,
          "tvl": 635035539
        },
        {
          "date": 1782345600,
          "tvl": 620487507
        },
        {
          "date": 1782432000,
          "tvl": 622885515
        },
        {
          "date": 1782518400,
          "tvl": 628067492
        },
        {
          "date": 1782604800,
          "tvl": 625212959
        },
        {
          "date": 1782691200,
          "tvl": 619206184
        },
        {
          "date": 1782733895,
          "tvl": 613097129
        }
      ],
      "aiSummary": "",
      "tweets": [
        {
          "id": "2071574460444905808",
          "fullText": "What's actually next for RWAs &amp; bStocks? 🤔\n\nWe're sitting down with @TrustWallet, @BNBCHAIN, @PancakeSwap &amp; @VenusProtocol to talk through exactly that.\n\n🗓️ June 30 · 12PM UTC. \n\nBring your questions 👇\n\nhttps://t.co/28aRfYXyPf",
          "createdAt": "Mon Jun 29 12:40:14 +0000 2026",
          "twitterUrl": "https://twitter.com/lista_dao/status/2071574460444905808",
          "likeCount": 19,
          "bookmarkCount": 0,
          "retweetCount": 0,
          "replyCount": 5,
          "viewCount": 3946
        },
        {
          "id": "2071526590463574510",
          "fullText": "Swap bStocks on @TrustWallet. Earn 37% with Lista.\n\n1️⃣ Swap any stablecoin to bStocks on Trust Wallet\n2️⃣ Deposit it on @lista_dao\n3️⃣ Earn 37% on your $SPCXB 📈\n\nShare a total of 200K rewards with ongoing campaigns! https://t.co/tCLdhRr56P",
          "createdAt": "Mon Jun 29 09:30:00 +0000 2026",
          "twitterUrl": "https://twitter.com/lista_dao/status/2071526590463574510",
          "likeCount": 41,
          "bookmarkCount": 3,
          "retweetCount": 1,
          "replyCount": 5,
          "viewCount": 8638,
          "thumbnailUrl": "https://pbs.twimg.com/media/HL-KEDwW8AAgcBG.jpg"
        },
        {
          "id": "2071398244744118554",
          "fullText": "233K $LISTA Weekly Emissions🔵\n\nJun 29th ~ Jul 5th\n\n🔹 USDC &amp; USDT LP Markets: 120.7K $LISTA\n🔹 Lista USDT &amp; USDC Savings Vault (Ethereum): 90K $LISTA\n🔹 RockawayX USDT Vault: 15K $LISTA\n🔹 Lista USDC Vault: 4.5K $LISTA\n🔹 Others: 4.1K $LISTA\n\nhttps://t.co/PDiQ9GgT1I https://t.co/kJSJ4K2ZI1",
          "createdAt": "Mon Jun 29 01:00:00 +0000 2026",
          "twitterUrl": "https://twitter.com/lista_dao/status/2071398244744118554",
          "likeCount": 33,
          "bookmarkCount": 1,
          "retweetCount": 23,
          "replyCount": 2,
          "viewCount": 10621,
          "thumbnailUrl": "https://pbs.twimg.com/media/HL8LfzcW4AAhuW3.png"
        },
        {
          "id": "2070484725765136723",
          "fullText": "Take A Loan From @BinanceWallet And Get Paid!\n\nBest rates:\n🔸sUSD1+/USD1: -6.98%\n🔸XAUT/U: -3.12%\n🔸slisBNB/U: -2.18%\n🔸BTCB/U: -1.5%\n🔸wBWTH/USDT: -1.93%\n\nJoin today! https://t.co/DAk3lKJpkk",
          "createdAt": "Fri Jun 26 12:30:01 +0000 2026",
          "twitterUrl": "https://twitter.com/lista_dao/status/2070484725765136723",
          "likeCount": 51,
          "bookmarkCount": 0,
          "retweetCount": 3,
          "replyCount": 2,
          "viewCount": 9806,
          "thumbnailUrl": "https://pbs.twimg.com/media/HLvHF6tWgAATd43.jpg"
        },
        {
          "id": "2070465228949656014",
          "fullText": "Audited &amp; transparent. 🔒\n\nSecurity is not a one-time checkbox.\n\nRegular independent audits are part of how we build trust.",
          "createdAt": "Fri Jun 26 11:12:32 +0000 2026",
          "twitterUrl": "https://twitter.com/lista_dao/status/2070465228949656014",
          "likeCount": 28,
          "bookmarkCount": 0,
          "retweetCount": 2,
          "replyCount": 6,
          "viewCount": 10406
        }
      ]
    },
    {
      "twitterHandle": "hyperlendx",
      "displayName": "HyperLend",
      "defiLlamaSlug": "hyperlend-pooled",
      "profilePicture": "https://pbs.twimg.com/profile_images/2011062303932678145/a5-fTMGC_normal.jpg",
      "tvl": 672173076.57284,
      "tvlHistory": [
        {
          "date": 1780185600,
          "tvl": 524343429
        },
        {
          "date": 1780272000,
          "tvl": 552209780
        },
        {
          "date": 1780358400,
          "tvl": 549767108
        },
        {
          "date": 1780444800,
          "tvl": 513687575
        },
        {
          "date": 1780531200,
          "tvl": 527691351
        },
        {
          "date": 1780617600,
          "tvl": 462921077
        },
        {
          "date": 1780704000,
          "tvl": 416186218
        },
        {
          "date": 1780790400,
          "tvl": 404242655
        },
        {
          "date": 1780876800,
          "tvl": 427957546
        },
        {
          "date": 1780963200,
          "tvl": 440293957
        },
        {
          "date": 1781049600,
          "tvl": 380781463
        },
        {
          "date": 1781136000,
          "tvl": 358139196
        },
        {
          "date": 1781222400,
          "tvl": 394165155
        },
        {
          "date": 1781308800,
          "tvl": 403936433
        },
        {
          "date": 1781395200,
          "tvl": 407751629
        },
        {
          "date": 1781481600,
          "tvl": 422679424
        },
        {
          "date": 1781568000,
          "tvl": 442317177
        },
        {
          "date": 1781654400,
          "tvl": 491135323
        },
        {
          "date": 1781740800,
          "tvl": 473383536
        },
        {
          "date": 1781827200,
          "tvl": 456180196
        },
        {
          "date": 1781913600,
          "tvl": 466326969
        },
        {
          "date": 1782000000,
          "tvl": 467706705
        },
        {
          "date": 1782086400,
          "tvl": 447675412
        },
        {
          "date": 1782172800,
          "tvl": 446164356
        },
        {
          "date": 1782259200,
          "tvl": 423215328
        },
        {
          "date": 1782345600,
          "tvl": 431377111
        },
        {
          "date": 1782432000,
          "tvl": 429873540
        },
        {
          "date": 1782518400,
          "tvl": 435761513
        },
        {
          "date": 1782604800,
          "tvl": 418913816
        },
        {
          "date": 1782691200,
          "tvl": 409119894
        },
        {
          "date": 1782733223,
          "tvl": 420032514
        }
      ],
      "aiSummary": "",
      "tweets": [
        {
          "id": "2069756522284847550",
          "fullText": "As part of our pursuit of continually refining and upgrading protocol security measures HyperLend is today introducing our newly created Veto Council.\n\nThe Veto Council is a protective board made up of close partners, investors and key Hyperliquid community members.\n\nThe Council",
          "createdAt": "Wed Jun 24 12:16:23 +0000 2026",
          "twitterUrl": "https://twitter.com/hyperlendx/status/2069756522284847550",
          "likeCount": 161,
          "bookmarkCount": 8,
          "retweetCount": 22,
          "replyCount": 37,
          "viewCount": 17976
        },
        {
          "id": "2067941865781920132",
          "fullText": "It's been 3 months since we launched the Stake &amp; Save program, so its time for our first ever HPL Staking quarterly review.\n\nOver the first 3 months of the Stake &amp; Save program borrowers have been paid out over $40,000 in borrow rebates, which equates to approximately 18% of",
          "createdAt": "Fri Jun 19 12:05:35 +0000 2026",
          "twitterUrl": "https://twitter.com/hyperlendx/status/2067941865781920132",
          "likeCount": 73,
          "bookmarkCount": 6,
          "retweetCount": 15,
          "replyCount": 61,
          "viewCount": 11494
        },
        {
          "id": "2067593469594353917",
          "fullText": "With final markets settling across the Hyperliquid ecosystem we would like to remind our users of the pending shutdown of USDH.\n\nHyperLend recommends that users repay any outstanding USDH debt and convert any supplied USDH to USDC.\n\nSee QT for methods to convert USDH.",
          "createdAt": "Thu Jun 18 13:01:11 +0000 2026",
          "twitterUrl": "https://twitter.com/hyperlendx/status/2067593469594353917",
          "likeCount": 35,
          "bookmarkCount": 2,
          "retweetCount": 45,
          "replyCount": 32,
          "viewCount": 7724
        },
        {
          "id": "2055093769406464149",
          "fullText": "Sunsetting USDH on HyperLend\n\nIn light of todays announcement that USDH will begin winding down operations on Hyperliquid we have made the decision to begin the process of sunsetting USDH borrowing and lending on HyperLend.\n\nWithin 48 hours users will no longer be able to supply",
          "createdAt": "Fri May 15 01:11:51 +0000 2026",
          "twitterUrl": "https://twitter.com/hyperlendx/status/2055093769406464149",
          "likeCount": 141,
          "bookmarkCount": 4,
          "retweetCount": 16,
          "replyCount": 3,
          "viewCount": 10626
        },
        {
          "id": "2054609546425839971",
          "fullText": "\"HyperLend exits Q1 2026 as the leading lending venue in the Hyperliquid ecosystem\"\n\nHyperliquid's Credit Layer continues to establish itself as a core piece of the house of all finance.\n\nRead the full report from @Blockworks below.",
          "createdAt": "Wed May 13 17:07:43 +0000 2026",
          "twitterUrl": "https://twitter.com/hyperlendx/status/2054609546425839971",
          "likeCount": 72,
          "bookmarkCount": 5,
          "retweetCount": 14,
          "replyCount": 15,
          "viewCount": 16790
        }
      ]
    },
    {
      "twitterHandle": "elementaldefi",
      "displayName": "Elemental ⬡",
      "defiLlamaSlug": "elemental",
      "profilePicture": "https://pbs.twimg.com/profile_images/1884484151463874560/IieI8_rA_normal.jpg",
      "tvl": 0,
      "tvlHistory": [],
      "aiSummary": "",
      "tweets": [
        {
          "id": "2069821355961504014",
          "fullText": "$USDG yields looking good right now ;)\n\nNot too shabby for $USDC too.\n\nWhich vault are you in? https://t.co/0QiiWcEyPR",
          "createdAt": "Wed Jun 24 16:34:01 +0000 2026",
          "twitterUrl": "https://twitter.com/elementaldefi/status/2069821355961504014",
          "likeCount": 14,
          "bookmarkCount": 0,
          "retweetCount": 1,
          "replyCount": 4,
          "viewCount": 662,
          "thumbnailUrl": "https://pbs.twimg.com/media/HLl7fvdXoAAWTHE.png"
        },
        {
          "id": "2069686434823643234",
          "fullText": "Elemental logo on a @superteam jersey? 👀👀",
          "createdAt": "Wed Jun 24 07:37:53 +0000 2026",
          "twitterUrl": "https://twitter.com/elementaldefi/status/2069686434823643234",
          "likeCount": 13,
          "bookmarkCount": 0,
          "retweetCount": 1,
          "replyCount": 1,
          "viewCount": 468
        },
        {
          "id": "2062112485461872653",
          "fullText": "Elemental gud tech 🤝",
          "createdAt": "Wed Jun 03 10:01:43 +0000 2026",
          "twitterUrl": "https://twitter.com/elementaldefi/status/2062112485461872653",
          "likeCount": 7,
          "bookmarkCount": 1,
          "retweetCount": 0,
          "replyCount": 1,
          "viewCount": 403
        },
        {
          "id": "2071230773727007089",
          "fullText": "We facilitated another $180k market sell order for $ONyc that was executed via a @kamino flash loan.\n\nPrice?\n\nDidn't break a sweat.\n\nOur new Orca Vault continues to do amazing plumbing for Solana DeFi. https://t.co/2NsqWQcFPI",
          "createdAt": "Sun Jun 28 13:54:32 +0000 2026",
          "twitterUrl": "https://twitter.com/elementaldefi/status/2071230773727007089",
          "likeCount": 19,
          "bookmarkCount": 1,
          "retweetCount": 0,
          "replyCount": 2,
          "viewCount": 1186,
          "thumbnailUrl": "https://pbs.twimg.com/media/HL585RBa4AIhBc1.jpg"
        },
        {
          "id": "2068721899786641629",
          "fullText": "🚨 New Launch: USDC Orca Vault\n\nThe USDC Orca Vault provides liquidity for real-world asset (RWA) pairs, with deployment isolated to Orca.\n\nThis vault is in partnership with @orca_so @onrefinance 🤝\n\n1/ https://t.co/xyfy3FJogx",
          "createdAt": "Sun Jun 21 15:45:10 +0000 2026",
          "twitterUrl": "https://twitter.com/elementaldefi/status/2068721899786641629",
          "likeCount": 41,
          "bookmarkCount": 4,
          "retweetCount": 10,
          "replyCount": 7,
          "viewCount": 12084,
          "thumbnailUrl": "https://pbs.twimg.com/media/HLWSfSXa4AAacq2.jpg"
        }
      ]
    },
    {
      "twitterHandle": "xBartega",
      "displayName": "Bartega | Kamino",
      "defiLlamaSlug": "",
      "profilePicture": "https://pbs.twimg.com/profile_images/1969454584155209729/SPDA0l3R_normal.png",
      "tvl": 0,
      "tvlHistory": [],
      "aiSummary": "",
      "tweets": [
        {
          "id": "2071541316786254134",
          "fullText": "PT-ONyc is paying a higher fixed yield than holding ONyc right now\n\nsplit into principal (PT) and yield (YT) on @ExponentFinance,  the airdrop speculators bid up YT \n\nthat pushes PT to a deeper discount, and a deeper discount is just a higher fixed return locked in",
          "createdAt": "Mon Jun 29 10:28:31 +0000 2026",
          "twitterUrl": "https://twitter.com/xBartega/status/2071541316786254134",
          "likeCount": 7,
          "bookmarkCount": 0,
          "retweetCount": 1,
          "replyCount": 0,
          "viewCount": 370
        },
        {
          "id": "2070180054051529056",
          "fullText": "for kamino security is number one priority, spending over $3M per year because user safety is not a narrative\n\nread the full opsec breakdown here",
          "createdAt": "Thu Jun 25 16:19:21 +0000 2026",
          "twitterUrl": "https://twitter.com/xBartega/status/2070180054051529056",
          "likeCount": 18,
          "bookmarkCount": 0,
          "retweetCount": 1,
          "replyCount": 3,
          "viewCount": 784
        },
        {
          "id": "2069836908906094763",
          "fullText": "solana's always had the activity, the question is how to make activity correlate to SOL value accrual\n\nsome interesting proposals coming up in the near future that could help tie the two together",
          "createdAt": "Wed Jun 24 17:35:49 +0000 2026",
          "twitterUrl": "https://twitter.com/xBartega/status/2069836908906094763",
          "likeCount": 7,
          "bookmarkCount": 1,
          "retweetCount": 0,
          "replyCount": 1,
          "viewCount": 384
        },
        {
          "id": "2069828283324158384",
          "fullText": "PRIME scaled to over $500M market size on Kamino during a quarter which saw crypto markets significantly shrinking \n\nthe shift on solana to high quality collaterals with productive yields has been seismic\n\nkamino's isolated market infrastructure has been essential to this growth",
          "createdAt": "Wed Jun 24 17:01:32 +0000 2026",
          "twitterUrl": "https://twitter.com/xBartega/status/2069828283324158384",
          "likeCount": 18,
          "bookmarkCount": 2,
          "retweetCount": 2,
          "replyCount": 0,
          "viewCount": 921
        },
        {
          "id": "2068702972335243264",
          "fullText": "proud to shill sol on the daily https://t.co/FqsDe3cuQb",
          "createdAt": "Sun Jun 21 14:29:57 +0000 2026",
          "twitterUrl": "https://twitter.com/xBartega/status/2068702972335243264",
          "likeCount": 11,
          "bookmarkCount": 0,
          "retweetCount": 0,
          "replyCount": 0,
          "viewCount": 518,
          "thumbnailUrl": "https://pbs.twimg.com/media/HLWCSX0WoAE4asm.jpg"
        }
      ]
    },
    {
      "twitterHandle": "kamino_swap",
      "displayName": "Kamino Swap",
      "defiLlamaSlug": "",
      "profilePicture": "https://pbs.twimg.com/profile_images/1999402473132277761/gpxrnDjz_normal.jpg",
      "tvl": 0,
      "tvlHistory": [],
      "aiSummary": "",
      "tweets": [
        {
          "id": "2070548683301499205",
          "fullText": "https://t.co/ix2oY3qd48",
          "createdAt": "Fri Jun 26 16:44:09 +0000 2026",
          "twitterUrl": "https://twitter.com/kamino_swap/status/2070548683301499205",
          "likeCount": 34,
          "bookmarkCount": 0,
          "retweetCount": 1,
          "replyCount": 2,
          "viewCount": 934,
          "thumbnailUrl": "https://pbs.twimg.com/media/HLwRCB8XwAAAIcB.jpg"
        },
        {
          "id": "2069364882865058197",
          "fullText": "When migrating from one debt asset to another you swap via Kamino Swap\n\nThat means you refinance at the best available price across 11 venues\n\nThe same execution layer behind Multiply entries, Repay With Collateral &amp; single asset Liquidity deposit\n\nNow refinancing debt too",
          "createdAt": "Tue Jun 23 10:20:09 +0000 2026",
          "twitterUrl": "https://twitter.com/kamino_swap/status/2069364882865058197",
          "likeCount": 11,
          "bookmarkCount": 0,
          "retweetCount": 0,
          "replyCount": 1,
          "viewCount": 390
        },
        {
          "id": "2067937747227038177",
          "fullText": "As @solana spot volume surpasses major CEXs, Kamino Swap remains the only venue with real-time CEX price comparisons side-by-side on all major pairs\n\nRoute-vs-route shows the best price on chain, but when swapping at size you need a true comparison between on and offchain pricing",
          "createdAt": "Fri Jun 19 11:49:14 +0000 2026",
          "twitterUrl": "https://twitter.com/kamino_swap/status/2067937747227038177",
          "likeCount": 13,
          "bookmarkCount": 0,
          "retweetCount": 0,
          "replyCount": 2,
          "viewCount": 365
        },
        {
          "id": "2067196926685061615",
          "fullText": "Swap Top 5: @xStocksFi Edition\n\nTokenised equities set a record of ~$150M in 24hr spot volume on @Solana \n\nSPCXx took the top spot in SpaceX's IPO week on Kamino Swap\n\nCRCLx entered the top 5 while arriving in Kamino Lend xStocks Market, lend it, long it, &amp; earn xPoints on it now https://t.co/PH3Xkwz4wc",
          "createdAt": "Wed Jun 17 10:45:28 +0000 2026",
          "twitterUrl": "https://twitter.com/kamino_swap/status/2067196926685061615",
          "likeCount": 92,
          "bookmarkCount": 4,
          "retweetCount": 17,
          "replyCount": 20,
          "viewCount": 13509,
          "thumbnailUrl": "https://pbs.twimg.com/media/HLAodiVWYAE-F_H.jpg"
        },
        {
          "id": "2066470374489907624",
          "fullText": "$SPCX has traded every day since Friday, weekend included, with ~$90M volume while the traditional markets were closed\n\nThis continuous, 27/4 trading was made possible thanks to @sunrise bringing the SPCX market to Solana \n\nTrade SPCX on Kamino Swap now with Zero fees https://t.co/hP8di82EDz",
          "createdAt": "Mon Jun 15 10:38:25 +0000 2026",
          "twitterUrl": "https://twitter.com/kamino_swap/status/2066470374489907624",
          "likeCount": 119,
          "bookmarkCount": 4,
          "retweetCount": 23,
          "replyCount": 29,
          "viewCount": 18186,
          "thumbnailUrl": "https://pbs.twimg.com/media/HK2TtlNWUAAJdK_.jpg"
        }
      ]
    },
    {
      "twitterHandle": "kamino_liq",
      "displayName": "Kamino Liquidity",
      "defiLlamaSlug": "",
      "profilePicture": "https://pbs.twimg.com/profile_images/1999402728242528257/Ix3W_1ik_normal.jpg",
      "tvl": 0,
      "tvlHistory": [],
      "aiSummary": "",
      "tweets": [
        {
          "id": "2071554088332922944",
          "fullText": "The liquidity layer institutions can build on\n\nKamino's automated vaults have run 4+ years without a single incident\n\nThat same infrastructure provides the depth RWAs need to trade at size, with over 30% of Liquidity TVL now in RWAs\n\nKamino is where assets scale https://t.co/L6dKZbhEGW",
          "createdAt": "Mon Jun 29 11:19:16 +0000 2026",
          "twitterUrl": "https://twitter.com/kamino_liq/status/2071554088332922944",
          "likeCount": 17,
          "bookmarkCount": 0,
          "retweetCount": 0,
          "replyCount": 2,
          "viewCount": 382,
          "thumbnailUrl": "https://pbs.twimg.com/media/HL-jdLsXkAEIB2O.jpg"
        },
        {
          "id": "2070527906179088880",
          "fullText": "Stablecoin yield on Kamino Liquidity doesn't depend on borrow demand\n\nIn lending your stablecoin APY lives on utilisation - if borrowers exit, the yield drops \n\nLiquidity has no borrowers to depend on, just:\n\n- Incentives\n- Trading fees\n- Instant withdrawal and no utilisation cap https://t.co/F0CL7vLyCY",
          "createdAt": "Fri Jun 26 15:21:36 +0000 2026",
          "twitterUrl": "https://twitter.com/kamino_liq/status/2070527906179088880",
          "likeCount": 18,
          "bookmarkCount": 0,
          "retweetCount": 0,
          "replyCount": 0,
          "viewCount": 423,
          "thumbnailUrl": "https://pbs.twimg.com/media/HLv-FT1WAAAjOe5.jpg"
        },
        {
          "id": "2070098535832297580",
          "fullText": "JTO-JitoSOL earned more in trading fees for LPs than any other Kamino pool this week\n\nLiquidity providers earned over $9K in fees while also capturing:\n\n- JTO incentives\n- JitoSOL native staking yield\n\nThe strategy is up 75.3% over the last 90D vs holding SOL https://t.co/YGOoQr1M1k",
          "createdAt": "Thu Jun 25 10:55:26 +0000 2026",
          "twitterUrl": "https://twitter.com/kamino_liq/status/2070098535832297580",
          "likeCount": 13,
          "bookmarkCount": 0,
          "retweetCount": 2,
          "replyCount": 0,
          "viewCount": 313,
          "thumbnailUrl": "https://pbs.twimg.com/media/HLp3hyCWkAAKPJr.jpg"
        },
        {
          "id": "2069748654164898060",
          "fullText": "Every correlated pair on Kamino keeps impermanent loss low while highly concentrated liquidity boosts fees\n\n- Stablecoins: pegged to the dollar\n- SOL &amp; LSTs: SOL exposure &amp; staking yield\n- Restaked &amp; base assets: token exposure plus restaking yield\n\nKamino has a pool for everyone https://t.co/H2hIO0vHf9",
          "createdAt": "Wed Jun 24 11:45:07 +0000 2026",
          "twitterUrl": "https://twitter.com/kamino_liq/status/2069748654164898060",
          "likeCount": 10,
          "bookmarkCount": 0,
          "retweetCount": 0,
          "replyCount": 1,
          "viewCount": 211,
          "thumbnailUrl": "https://pbs.twimg.com/media/HLk5RliXoAAG7_Q.jpg"
        },
        {
          "id": "2069412637650063360",
          "fullText": "~16% APY right now with PYUSD-PRIME on Kamino Liquidity:\n\n- $4,000 PYUSD a week incentives\n- HELOC yield from PRIME issued by @hastrafi\n- Fees via trading volume\n\nTop stablecoin rates, paired with RWA native, productive yield \n\nScaling real world assets on Solana https://t.co/8ewqZ1YEKK",
          "createdAt": "Tue Jun 23 13:29:55 +0000 2026",
          "twitterUrl": "https://twitter.com/kamino_liq/status/2069412637650063360",
          "likeCount": 25,
          "bookmarkCount": 1,
          "retweetCount": 3,
          "replyCount": 1,
          "viewCount": 608,
          "thumbnailUrl": "https://pbs.twimg.com/media/HLgHt0tW4AA4xH0.jpg"
        }
      ]
    }
  ],
  "highlights": {
    "mostLiked": {
      "twitterHandle": "deficarrot",
      "tweetIndex": 1,
      "likeCount": 826
    },
    "mostBookmarked": {
      "twitterHandle": "deficarrot",
      "tweetIndex": 1,
      "bookmarkCount": 119
    },
    "mostInteresting": {
      "twitterHandle": "deficarrot",
      "tweetIndex": 1,
      "reason": "Highest engagement tweet"
    }
  }
}