{
  "timestamp": "2026-03-03T04:30:29.531Z",
  "version": 2,
  "stats": {
    "lendMarketSize": 2858354752,
    "lendVaultDeposits": 554983987,
    "liquidityDeposits": 216477324,
    "liquidityFeesGenerated": 41628477,
    "multiplyDeposits": 538076822,
    "multiplyBorrows": 427311051,
    "borrowMarketSize": 3055181276,
    "borrowActiveBorrows": 1133745943
  },
  "borrow": [
    {
      "asset": "PRIME",
      "market": "Prime Market",
      "totalSupply": 303720000,
      "totalBorrow": 0,
      "liqLtv": 91,
      "supplyApy": 0,
      "borrowApy": 0
    },
    {
      "asset": "USDC",
      "market": "Prime Market",
      "totalSupply": 187100000,
      "totalBorrow": 178860000,
      "liqLtv": 0,
      "supplyApy": 6.2,
      "borrowApy": 7.24
    },
    {
      "asset": "CASH",
      "market": "Prime Market",
      "totalSupply": 49550000,
      "totalBorrow": 47160000,
      "liqLtv": 0,
      "supplyApy": 6.06,
      "borrowApy": 7.11
    },
    {
      "asset": "PYUSD",
      "market": "Prime Market",
      "totalSupply": 21910000,
      "totalBorrow": 19720000,
      "liqLtv": 0,
      "supplyApy": 5.16,
      "borrowApy": 6.41
    },
    {
      "asset": "USDS",
      "market": "Prime Market",
      "totalSupply": 10340000,
      "totalBorrow": 8600000,
      "liqLtv": 0,
      "supplyApy": 7.31,
      "borrowApy": 6.41
    },
    {
      "asset": "SOL",
      "market": "Main Market",
      "totalSupply": 279040000,
      "totalBorrow": 259279999.99999997,
      "liqLtv": 75,
      "supplyApy": 12.190000000000001,
      "borrowApy": 10.55
    },
    {
      "asset": "USDC",
      "market": "Main Market",
      "totalSupply": 286930000,
      "totalBorrow": 166900000,
      "liqLtv": 90,
      "supplyApy": 1.27,
      "borrowApy": 3.08
    },
    {
      "asset": "PYUSD",
      "market": "Main Market",
      "totalSupply": 274910000,
      "totalBorrow": 155530000,
      "liqLtv": 90,
      "supplyApy": 0.57,
      "borrowApy": 1.77
    },
    {
      "asset": "cbBTC",
      "market": "Main Market",
      "totalSupply": 216200000,
      "totalBorrow": 851000,
      "liqLtv": 80,
      "supplyApy": 3.09,
      "borrowApy": 0.03
    },
    {
      "asset": "JUPSOL",
      "market": "Main Market",
      "totalSupply": 112030000,
      "totalBorrow": 355980,
      "liqLtv": 60,
      "supplyApy": 0,
      "borrowApy": 1.31
    },
    {
      "asset": "JITOSOL",
      "market": "Main Market",
      "totalSupply": 79670000,
      "totalBorrow": 688310,
      "liqLtv": 60,
      "supplyApy": 1.86,
      "borrowApy": 1.35
    },
    {
      "asset": "fwdSOL",
      "market": "Main Market",
      "totalSupply": 53160000,
      "totalBorrow": 0,
      "liqLtv": 55,
      "supplyApy": 0,
      "borrowApy": 0
    },
    {
      "asset": "USDG",
      "market": "Main Market",
      "totalSupply": 46020000,
      "totalBorrow": 30980000,
      "liqLtv": 90,
      "supplyApy": 2.81,
      "borrowApy": 10.07
    },
    {
      "asset": "MSOL",
      "market": "Main Market",
      "totalSupply": 28890000,
      "totalBorrow": 365240,
      "liqLtv": 60,
      "supplyApy": 0,
      "borrowApy": 1.37
    },
    {
      "asset": "xBTC",
      "market": "Main Market",
      "totalSupply": 22600000,
      "totalBorrow": 324940,
      "liqLtv": 80,
      "supplyApy": 4.73,
      "borrowApy": 0.09
    },
    {
      "asset": "USDS",
      "market": "Main Market",
      "totalSupply": 20460000,
      "totalBorrow": 7540000,
      "liqLtv": 90,
      "supplyApy": 2.98,
      "borrowApy": 2.57
    },
    {
      "asset": "STKESOL",
      "market": "Main Market",
      "totalSupply": 13340000,
      "totalBorrow": 0,
      "liqLtv": 55,
      "supplyApy": 2.42,
      "borrowApy": 0
    },
    {
      "asset": "USDT",
      "market": "Main Market",
      "totalSupply": 9250000,
      "totalBorrow": 5760000,
      "liqLtv": 90,
      "supplyApy": 1.03,
      "borrowApy": 2.49
    },
    {
      "asset": "CASH",
      "market": "Main Market",
      "totalSupply": 6880000,
      "totalBorrow": 4890000,
      "liqLtv": 90,
      "supplyApy": 2.38,
      "borrowApy": 8.350000000000001
    },
    {
      "asset": "FBTC",
      "market": "Main Market",
      "totalSupply": 6830000,
      "totalBorrow": 0,
      "liqLtv": 80,
      "supplyApy": 0,
      "borrowApy": 0
    },
    {
      "asset": "ETH",
      "market": "Main Market",
      "totalSupply": 3560000,
      "totalBorrow": 722430,
      "liqLtv": 80,
      "supplyApy": 0.18,
      "borrowApy": 1.12
    },
    {
      "asset": "USD1",
      "market": "Main Market",
      "totalSupply": 2710000,
      "totalBorrow": 2089999.9999999998,
      "liqLtv": 0,
      "supplyApy": 3.25,
      "borrowApy": 5.39
    },
    {
      "asset": "EURC",
      "market": "Main Market",
      "totalSupply": 1370000,
      "totalBorrow": 378250,
      "liqLtv": 0,
      "supplyApy": 0.29,
      "borrowApy": 2.62
    },
    {
      "asset": "LSTs",
      "market": "Main Market",
      "totalSupply": 307140000,
      "totalBorrow": 510090,
      "liqLtv": 55,
      "supplyApy": 0,
      "borrowApy": 0
    }
  ],
  "liquidity": [
    {
      "pair": "PYUSD-USDC",
      "feesApy7d": 5.5,
      "volume7d": 10470000,
      "tvl": 29360000,
      "dex": ""
    },
    {
      "pair": "USDS-USDC",
      "feesApy7d": 6.26,
      "volume7d": 16910000,
      "tvl": 28590000,
      "dex": ""
    },
    {
      "pair": "syrupUSDC-USDC",
      "feesApy7d": 0.6,
      "volume7d": 30210000,
      "tvl": 25180000,
      "dex": ""
    },
    {
      "pair": "PRIME-CASH",
      "feesApy7d": 1.13,
      "volume7d": 44670000,
      "tvl": 19750000,
      "dex": ""
    },
    {
      "pair": "CASH-USDC",
      "feesApy7d": 5.28,
      "volume7d": 22090000,
      "tvl": 17100000,
      "dex": ""
    },
    {
      "pair": "USDS-USDC",
      "feesApy7d": 6.51,
      "volume7d": 2020000,
      "tvl": 14170000,
      "dex": ""
    },
    {
      "pair": "USDG-USDC",
      "feesApy7d": 0.21,
      "volume7d": 5400000,
      "tvl": 12700000,
      "dex": ""
    },
    {
      "pair": "JITOSOL-SOL",
      "feesApy7d": 4.3,
      "volume7d": 23230000,
      "tvl": 7290000,
      "dex": ""
    },
    {
      "pair": "wM-USDC",
      "feesApy7d": 0,
      "volume7d": 0,
      "tvl": 3250000,
      "dex": ""
    },
    {
      "pair": "JITOSOL-SOL",
      "feesApy7d": 5.23,
      "volume7d": 13990000,
      "tvl": 3220000,
      "dex": ""
    },
    {
      "pair": "USDu-USDC",
      "feesApy7d": 12.24,
      "volume7d": 796570,
      "tvl": 3020000,
      "dex": ""
    },
    {
      "pair": "USDG-syrupUSDC",
      "feesApy7d": 0.51,
      "volume7d": 3310000,
      "tvl": 2510000,
      "dex": ""
    },
    {
      "pair": "wYLDS-CASH",
      "feesApy7d": 0.32,
      "volume7d": 1570000,
      "tvl": 2410000,
      "dex": ""
    },
    {
      "pair": "deJAAA-USDC",
      "feesApy7d": 0,
      "volume7d": 0,
      "tvl": 2180000,
      "dex": ""
    }
  ],
  "multiply": [
    {
      "supply": "PRIME",
      "market": "Prime Market",
      "borrowToken": "CASH",
      "maxNetApy": 10.37,
      "maxLeverage": "8.3x",
      "liqAvailable": 0,
      "supplied": 54630000,
      "strategy": "RWA Loop"
    },
    {
      "supply": "PRIME",
      "market": "Prime Market",
      "borrowToken": "USDC",
      "maxNetApy": 9.43,
      "maxLeverage": "8.3x",
      "liqAvailable": 0,
      "supplied": 173730000,
      "strategy": "RWA Loop"
    },
    {
      "supply": "PRIME",
      "market": "Prime Market",
      "borrowToken": "PYUSD",
      "maxNetApy": 15.48,
      "maxLeverage": "8.3x",
      "liqAvailable": 1780,
      "supplied": 21950000,
      "strategy": "RWA Loop"
    },
    {
      "supply": "PRIME",
      "market": "Prime Market",
      "borrowToken": "USDS",
      "maxNetApy": 15.48,
      "maxLeverage": "8.3x",
      "liqAvailable": 712420,
      "supplied": 8359999.999999999,
      "strategy": "RWA Loop"
    },
    {
      "supply": "JLP",
      "market": "JLP Market",
      "borrowToken": "USDC",
      "maxNetApy": 41.71,
      "maxLeverage": "6.2x",
      "liqAvailable": 29230000,
      "supplied": 31340000,
      "strategy": "Directional Leverage"
    },
    {
      "supply": "SOL",
      "market": "Main Market",
      "borrowToken": "USDC",
      "maxNetApy": 22.92,
      "maxLeverage": "3.8x",
      "liqAvailable": 120030000,
      "supplied": 694080,
      "strategy": "Directional Leverage"
    },
    {
      "supply": "syrupUSDC",
      "market": "Maple Market",
      "borrowToken": "USDC",
      "maxNetApy": 4.8,
      "maxLeverage": "8.3x",
      "liqAvailable": 1130000,
      "supplied": 8840000,
      "strategy": "RWA Loop"
    },
    {
      "supply": "INF",
      "market": "Sanctum Market",
      "borrowToken": "SOL",
      "maxNetApy": 13.05,
      "maxLeverage": "10x",
      "liqAvailable": 129100,
      "supplied": 1580000,
      "strategy": "SOL Loop"
    },
    {
      "supply": "rstSOL",
      "market": "rstSOL Leverage Market",
      "borrowToken": "SOL",
      "maxNetApy": 3.59,
      "maxLeverage": "5x",
      "liqAvailable": 0,
      "supplied": 27230,
      "strategy": "SOL Loop"
    },
    {
      "supply": "STKESOL",
      "market": "Main Market",
      "borrowToken": "SOL",
      "maxNetApy": 0,
      "maxLeverage": "7.7x",
      "liqAvailable": 19750000,
      "supplied": 6890000,
      "strategy": "SOL Loop"
    },
    {
      "supply": "USDC",
      "market": "Main Market",
      "borrowToken": "PYUSD",
      "maxNetApy": 0,
      "maxLeverage": "10x",
      "liqAvailable": 71990000,
      "supplied": 8240000,
      "strategy": "Stable Loop"
    },
    {
      "supply": "syrupUSDC",
      "market": "Maple Market",
      "borrowToken": "USDG",
      "maxNetApy": 10.31,
      "maxLeverage": "8.3x",
      "liqAvailable": 185550,
      "supplied": 1150000,
      "strategy": "RWA Loop"
    },
    {
      "supply": "syrupUSDC",
      "market": "Maple Market",
      "borrowToken": "USDS",
      "maxNetApy": 13.52,
      "maxLeverage": "8.3x",
      "liqAvailable": 110320,
      "supplied": 376760,
      "strategy": "RWA Loop"
    },
    {
      "supply": "syrupUSDC",
      "market": "Maple Market",
      "borrowToken": "CASH",
      "maxNetApy": 0,
      "maxLeverage": "8.3x",
      "liqAvailable": 701800,
      "supplied": 9090000,
      "strategy": "RWA Loop"
    },
    {
      "supply": "syrupUSDC",
      "market": "Maple Market",
      "borrowToken": "PYUSD",
      "maxNetApy": 10.74,
      "maxLeverage": "5x",
      "liqAvailable": 46360000,
      "supplied": 31340000,
      "strategy": "RWA Loop"
    },
    {
      "supply": "syrupUSDC",
      "market": "Maple Market",
      "borrowToken": "USD1",
      "maxNetApy": 0,
      "maxLeverage": "8.3x",
      "liqAvailable": 0,
      "supplied": 1090000,
      "strategy": "RWA Loop"
    },
    {
      "supply": "USDG",
      "market": "Main Market",
      "borrowToken": "PYUSD",
      "maxNetApy": 12.09,
      "maxLeverage": "10x",
      "liqAvailable": 71990000,
      "supplied": 1540000,
      "strategy": "Stable Loop"
    },
    {
      "supply": "ONyc",
      "market": "OnRe Market",
      "borrowToken": "USDC",
      "maxNetApy": 15.23,
      "maxLeverage": "2.5x",
      "liqAvailable": 2590000,
      "supplied": 13610000,
      "strategy": "RWA Loop"
    },
    {
      "supply": "ONyc",
      "market": "OnRe Market",
      "borrowToken": "USDG",
      "maxNetApy": 17.1,
      "maxLeverage": "2.5x",
      "liqAvailable": 106340,
      "supplied": 10350000,
      "strategy": "RWA Loop"
    },
    {
      "supply": "JLP",
      "market": "JLP Market",
      "borrowToken": "USDG",
      "maxNetApy": 37.12,
      "maxLeverage": "6.2x",
      "liqAvailable": 67290,
      "supplied": 875110,
      "strategy": "Directional Leverage"
    },
    {
      "supply": "JLP",
      "market": "JLP Market",
      "borrowToken": "USDT",
      "maxNetApy": 41.94,
      "maxLeverage": "6.2x",
      "liqAvailable": 2180000,
      "supplied": 3170000,
      "strategy": "Directional Leverage"
    },
    {
      "supply": "JLP",
      "market": "JLP Market",
      "borrowToken": "PYUSD",
      "maxNetApy": 41.47,
      "maxLeverage": "6.2x",
      "liqAvailable": 3150000,
      "supplied": 3990000,
      "strategy": "Directional Leverage"
    },
    {
      "supply": "JLP",
      "market": "JLP Market",
      "borrowToken": "USD1",
      "maxNetApy": 32.1,
      "maxLeverage": "6.2x",
      "liqAvailable": 133.6,
      "supplied": 84.71,
      "strategy": "Directional Leverage"
    },
    {
      "supply": "CASH",
      "market": "Main Market",
      "borrowToken": "PYUSD",
      "maxNetApy": 7.83,
      "maxLeverage": "10x",
      "liqAvailable": 71990000,
      "supplied": 3580000,
      "strategy": "Stable Loop"
    },
    {
      "supply": "SOL",
      "market": "Main Market",
      "borrowToken": "PYUSD",
      "maxNetApy": 26.65,
      "maxLeverage": "3.8x",
      "liqAvailable": 71990000,
      "supplied": 661060,
      "strategy": "Directional Leverage"
    },
    {
      "supply": "eUSX",
      "market": "Solstice Market",
      "borrowToken": "USX",
      "maxNetApy": 2.73,
      "maxLeverage": "4x",
      "liqAvailable": 4850000,
      "supplied": 62710,
      "strategy": "RWA Loop"
    },
    {
      "supply": "dSOL",
      "market": "Main Market",
      "borrowToken": "SOL",
      "maxNetApy": 0,
      "maxLeverage": "7.7x",
      "liqAvailable": 19750000,
      "supplied": 7820000,
      "strategy": "SOL Loop"
    },
    {
      "supply": "JUPSOL",
      "market": "Main Market",
      "borrowToken": "SOL",
      "maxNetApy": 0,
      "maxLeverage": "7.7x",
      "liqAvailable": 19750000,
      "supplied": 33750000,
      "strategy": "SOL Loop"
    },
    {
      "supply": "JUPSOL",
      "market": "Main Market",
      "borrowToken": "USDC",
      "maxNetApy": 11.77,
      "maxLeverage": "2.4x",
      "liqAvailable": 120030000,
      "supplied": 30800,
      "strategy": "Directional Leverage"
    },
    {
      "supply": "JITOSOL",
      "market": "Main Market",
      "borrowToken": "SOL",
      "maxNetApy": 0,
      "maxLeverage": "7.7x",
      "liqAvailable": 19750000,
      "supplied": 7480000,
      "strategy": "SOL Loop"
    },
    {
      "supply": "JITOSOL",
      "market": "Main Market",
      "borrowToken": "USDC",
      "maxNetApy": 10.26,
      "maxLeverage": "2.4x",
      "liqAvailable": 120030000,
      "supplied": 53920,
      "strategy": "Directional Leverage"
    },
    {
      "supply": "fwdSOL",
      "market": "Main Market",
      "borrowToken": "SOL",
      "maxNetApy": 0,
      "maxLeverage": "7.7x",
      "liqAvailable": 19750000,
      "supplied": 1380,
      "strategy": "SOL Loop"
    },
    {
      "supply": "dfdvSOL",
      "market": "Main Market",
      "borrowToken": "SOL",
      "maxNetApy": 0,
      "maxLeverage": "7.7x",
      "liqAvailable": 19750000,
      "supplied": 389050,
      "strategy": "SOL Loop"
    },
    {
      "supply": "JITOSOL",
      "market": "Jito Market",
      "borrowToken": "SOL",
      "maxNetApy": 0,
      "maxLeverage": "12.5x",
      "liqAvailable": 0,
      "supplied": 2690000,
      "strategy": "SOL Loop"
    },
    {
      "supply": "MSOL",
      "market": "Main Market",
      "borrowToken": "SOL",
      "maxNetApy": 0,
      "maxLeverage": "7.7x",
      "liqAvailable": 19750000,
      "supplied": 7430000,
      "strategy": "SOL Loop"
    },
    {
      "supply": "MSOL",
      "market": "Main Market",
      "borrowToken": "USDC",
      "maxNetApy": 10.07,
      "maxLeverage": "2.4x",
      "liqAvailable": 120030000,
      "supplied": 2200,
      "strategy": "Directional Leverage"
    },
    {
      "supply": "HSOL",
      "market": "Main Market",
      "borrowToken": "SOL",
      "maxNetApy": 0,
      "maxLeverage": "7.7x",
      "liqAvailable": 19750000,
      "supplied": 641170,
      "strategy": "SOL Loop"
    },
    {
      "supply": "bonkSOL",
      "market": "Main Market",
      "borrowToken": "SOL",
      "maxNetApy": 0,
      "maxLeverage": "7.7x",
      "liqAvailable": 19750000,
      "supplied": 15180000,
      "strategy": "SOL Loop"
    },
    {
      "supply": "BSOL",
      "market": "Main Market",
      "borrowToken": "SOL",
      "maxNetApy": 0,
      "maxLeverage": "7.7x",
      "liqAvailable": 19750000,
      "supplied": 13270000,
      "strategy": "SOL Loop"
    },
    {
      "supply": "VSOL",
      "market": "Main Market",
      "borrowToken": "SOL",
      "maxNetApy": 0,
      "maxLeverage": "7.7x",
      "liqAvailable": 19750000,
      "supplied": 11150000,
      "strategy": "SOL Loop"
    },
    {
      "supply": "CGNTSOL",
      "market": "Main Market",
      "borrowToken": "SOL",
      "maxNetApy": 0,
      "maxLeverage": "7.7x",
      "liqAvailable": 19750000,
      "supplied": 9950000,
      "strategy": "SOL Loop"
    },
    {
      "supply": "PSOL",
      "market": "Main Market",
      "borrowToken": "SOL",
      "maxNetApy": 0,
      "maxLeverage": "7.7x",
      "liqAvailable": 19750000,
      "supplied": 938850,
      "strategy": "SOL Loop"
    },
    {
      "supply": "PSOL",
      "market": "Main Market",
      "borrowToken": "CASH",
      "maxNetApy": 8.7,
      "maxLeverage": "1.8x",
      "liqAvailable": 1980000,
      "supplied": 15110,
      "strategy": "Directional Leverage"
    },
    {
      "supply": "MSOL",
      "market": "Marinade Market",
      "borrowToken": "SOL",
      "maxNetApy": 0,
      "maxLeverage": "10x",
      "liqAvailable": 291940,
      "supplied": 8600000,
      "strategy": "SOL Loop"
    },
    {
      "supply": "LAINESOL",
      "market": "Main Market",
      "borrowToken": "SOL",
      "maxNetApy": 0,
      "maxLeverage": "7.7x",
      "liqAvailable": 19750000,
      "supplied": 5330000,
      "strategy": "SOL Loop"
    },
    {
      "supply": "strongSOL",
      "market": "Main Market",
      "borrowToken": "SOL",
      "maxNetApy": 0,
      "maxLeverage": "7.7x",
      "liqAvailable": 19750000,
      "supplied": 4760000,
      "strategy": "SOL Loop"
    },
    {
      "supply": "BSOL",
      "market": "Solblaze Market",
      "borrowToken": "SOL",
      "maxNetApy": 0,
      "maxLeverage": "10x",
      "liqAvailable": 144410,
      "supplied": 3790000,
      "strategy": "SOL Loop"
    },
    {
      "supply": "bbSOL",
      "market": "Main Market",
      "borrowToken": "SOL",
      "maxNetApy": 0,
      "maxLeverage": "7.7x",
      "liqAvailable": 19750000,
      "supplied": 54070,
      "strategy": "SOL Loop"
    },
    {
      "supply": "JSOL",
      "market": "Main Market",
      "borrowToken": "SOL",
      "maxNetApy": 0,
      "maxLeverage": "7.7x",
      "liqAvailable": 19750000,
      "supplied": 2690000,
      "strategy": "SOL Loop"
    },
    {
      "supply": "lanternSOL",
      "market": "Main Market",
      "borrowToken": "SOL",
      "maxNetApy": 0,
      "maxLeverage": "7.7x",
      "liqAvailable": 19750000,
      "supplied": 2450000,
      "strategy": "SOL Loop"
    },
    {
      "supply": "nxSOL",
      "market": "Main Market",
      "borrowToken": "SOL",
      "maxNetApy": 0,
      "maxLeverage": "7.7x",
      "liqAvailable": 19750000,
      "supplied": 942740,
      "strategy": "SOL Loop"
    },
    {
      "supply": "picoSOL",
      "market": "Main Market",
      "borrowToken": "SOL",
      "maxNetApy": 0,
      "maxLeverage": "7.7x",
      "liqAvailable": 19750000,
      "supplied": 1250000,
      "strategy": "SOL Loop"
    },
    {
      "supply": "ezSOL",
      "market": "Jito Market",
      "borrowToken": "SOL",
      "maxNetApy": 0,
      "maxLeverage": "10x",
      "liqAvailable": 0,
      "supplied": 22160,
      "strategy": "SOL Loop"
    },
    {
      "supply": "TSLA",
      "market": "xxStocks Market",
      "borrowToken": "USDC",
      "maxNetApy": 12.22,
      "maxLeverage": "2.2x",
      "liqAvailable": 2840000,
      "supplied": 25830,
      "strategy": "Directional Leverage"
    },
    {
      "supply": "cbBTC",
      "market": "Main Market",
      "borrowToken": "USDC",
      "maxNetApy": 11.59,
      "maxLeverage": "4.8x",
      "liqAvailable": 120030000,
      "supplied": 32630.000000000004,
      "strategy": "Directional Leverage"
    },
    {
      "supply": "QQQ",
      "market": "xxStocks Market",
      "borrowToken": "USDC",
      "maxNetApy": 23.41,
      "maxLeverage": "3.3x",
      "liqAvailable": 2840000,
      "supplied": 556.69,
      "strategy": "Directional Leverage"
    },
    {
      "supply": "raSOL",
      "market": "Main Market",
      "borrowToken": "SOL",
      "maxNetApy": 0,
      "maxLeverage": "7.7x",
      "liqAvailable": 19750000,
      "supplied": 131840,
      "strategy": "SOL Loop"
    },
    {
      "supply": "SPY",
      "market": "xxStocks Market",
      "borrowToken": "USDC",
      "maxNetApy": 27.05,
      "maxLeverage": "3.7x",
      "liqAvailable": 2840000,
      "supplied": 14900,
      "strategy": "Directional Leverage"
    },
    {
      "supply": "BNSOL",
      "market": "Main Market",
      "borrowToken": "SOL",
      "maxNetApy": 0,
      "maxLeverage": "7.7x",
      "liqAvailable": 19750000,
      "supplied": 36740,
      "strategy": "SOL Loop"
    },
    {
      "supply": "xBTC",
      "market": "Main Market",
      "borrowToken": "USDC",
      "maxNetApy": 11.59,
      "maxLeverage": "4.8x",
      "liqAvailable": 120030000,
      "supplied": 1.95,
      "strategy": "Directional Leverage"
    },
    {
      "supply": "adraSOL",
      "market": "Main Market",
      "borrowToken": "SOL",
      "maxNetApy": 0,
      "maxLeverage": "7.7x",
      "liqAvailable": 19750000,
      "supplied": 8160,
      "strategy": "SOL Loop"
    }
  ]
}