{
  "timestamp": "2026-06-04T09:36:27.962Z",
  "version": 2,
  "stats": {
    "lendMarketSize": 2858354752,
    "lendVaultDeposits": 554983987,
    "liquidityDeposits": 149415935,
    "liquidityFeesGenerated": 42216551,
    "multiplyDeposits": 471770887,
    "multiplyBorrows": 363904989,
    "borrowMarketSize": 2551359095,
    "borrowActiveBorrows": 991752209
  },
  "borrow": [
    {
      "asset": "USDe",
      "market": "Prime Market",
      "totalSupply": 237150000,
      "totalBorrow": 1260,
      "liqLtv": 94,
      "supplyApy": 3.76,
      "borrowApy": 0.01
    },
    {
      "asset": "USDG",
      "market": "Prime Market",
      "totalSupply": 250250000,
      "totalBorrow": 205750000,
      "liqLtv": 0,
      "supplyApy": 1.71,
      "borrowApy": 2.31
    },
    {
      "asset": "PYUSD",
      "market": "Prime Market",
      "totalSupply": 100610000,
      "totalBorrow": 2720000,
      "liqLtv": 90,
      "supplyApy": 0,
      "borrowApy": 0.07
    },
    {
      "asset": "SOL",
      "market": "Main Market",
      "totalSupply": 194580000,
      "totalBorrow": 173770000,
      "liqLtv": 75,
      "supplyApy": 7.620000000000001,
      "borrowApy": 6.27
    },
    {
      "asset": "USDC",
      "market": "Main Market",
      "totalSupply": 139330000,
      "totalBorrow": 132530000,
      "liqLtv": 90,
      "supplyApy": 4.96,
      "borrowApy": 6.48
    },
    {
      "asset": "JUPSOL",
      "market": "Main Market",
      "totalSupply": 80900000,
      "totalBorrow": 249380,
      "liqLtv": 60,
      "supplyApy": 5.91,
      "borrowApy": 1.3
    },
    {
      "asset": "cbBTC",
      "market": "Main Market",
      "totalSupply": 68250000,
      "totalBorrow": 2290000,
      "liqLtv": 80,
      "supplyApy": 4.029999999999999,
      "borrowApy": 0.19
    },
    {
      "asset": "JITOSOL",
      "market": "Main Market",
      "totalSupply": 62170000,
      "totalBorrow": 374590,
      "liqLtv": 60,
      "supplyApy": 9.5,
      "borrowApy": 1.33
    },
    {
      "asset": "PYUSD",
      "market": "Main Market",
      "totalSupply": 56880000,
      "totalBorrow": 47570000,
      "liqLtv": 90,
      "supplyApy": 1.25,
      "borrowApy": 2.31
    },
    {
      "asset": "MSOL",
      "market": "Main Market",
      "totalSupply": 38010000,
      "totalBorrow": 279070,
      "liqLtv": 60,
      "supplyApy": 6.04,
      "borrowApy": 1.33
    },
    {
      "asset": "USDG",
      "market": "Main Market",
      "totalSupply": 28850000,
      "totalBorrow": 27050000,
      "liqLtv": 90,
      "supplyApy": 5.5,
      "borrowApy": 12.68
    },
    {
      "asset": "xBTC",
      "market": "Main Market",
      "totalSupply": 12910000,
      "totalBorrow": 465470,
      "liqLtv": 80,
      "supplyApy": 5.47,
      "borrowApy": 0.21
    },
    {
      "asset": "FBTC",
      "market": "Main Market",
      "totalSupply": 9440000,
      "totalBorrow": 0,
      "liqLtv": 80,
      "supplyApy": 0,
      "borrowApy": 0
    },
    {
      "asset": "STKESOL",
      "market": "Main Market",
      "totalSupply": 8119999.999999999,
      "totalBorrow": 0,
      "liqLtv": 55,
      "supplyApy": 8.42,
      "borrowApy": 0
    },
    {
      "asset": "USDT",
      "market": "Main Market",
      "totalSupply": 7730000,
      "totalBorrow": 6540000,
      "liqLtv": 90,
      "supplyApy": 3.34,
      "borrowApy": 5.07
    },
    {
      "asset": "USDS",
      "market": "Main Market",
      "totalSupply": 7400000,
      "totalBorrow": 5620000,
      "liqLtv": 90,
      "supplyApy": 4.48,
      "borrowApy": 4.64
    },
    {
      "asset": "ETH",
      "market": "Main Market",
      "totalSupply": 2570000,
      "totalBorrow": 1450000,
      "liqLtv": 80,
      "supplyApy": 1.38,
      "borrowApy": 3.1
    },
    {
      "asset": "EURC",
      "market": "Main Market",
      "totalSupply": 647270,
      "totalBorrow": 450670,
      "liqLtv": 0,
      "supplyApy": 1.85,
      "borrowApy": 4.67
    },
    {
      "asset": "CASH",
      "market": "Main Market",
      "totalSupply": 508540,
      "totalBorrow": 432170,
      "liqLtv": 90,
      "supplyApy": 3.4,
      "borrowApy": 5.13
    },
    {
      "asset": "USD1",
      "market": "Main Market",
      "totalSupply": 46000,
      "totalBorrow": 31460,
      "liqLtv": 0,
      "supplyApy": 2.55,
      "borrowApy": 4.84
    },
    {
      "asset": "LSTs",
      "market": "Main Market",
      "totalSupply": 219850000,
      "totalBorrow": 370060,
      "liqLtv": 55,
      "supplyApy": 0,
      "borrowApy": 0
    }
  ],
  "liquidity": [
    {
      "pair": "USDS-USDC",
      "feesApy7d": 7.23,
      "volume7d": 4350000,
      "tvl": 23710000,
      "dex": ""
    },
    {
      "pair": "syrupUSDC-USDC",
      "feesApy7d": 0.76,
      "volume7d": 30860000,
      "tvl": 20150000,
      "dex": ""
    },
    {
      "pair": "PYUSD-USDC",
      "feesApy7d": 7.17,
      "volume7d": 11150000,
      "tvl": 18990000,
      "dex": ""
    },
    {
      "pair": "USDS-USDC",
      "feesApy7d": 7.36,
      "volume7d": 453770,
      "tvl": 12420000,
      "dex": ""
    },
    {
      "pair": "USDG-USDC",
      "feesApy7d": 0.44,
      "volume7d": 9450000,
      "tvl": 10540000,
      "dex": ""
    },
    {
      "pair": "PRIME-CASH",
      "feesApy7d": 3.88,
      "volume7d": 77710000,
      "tvl": 10110000,
      "dex": ""
    },
    {
      "pair": "USDG-USDE",
      "feesApy7d": 0.76,
      "volume7d": 8500000,
      "tvl": 5520000,
      "dex": ""
    },
    {
      "pair": "CASH-USDC",
      "feesApy7d": 6.88,
      "volume7d": 6400000,
      "tvl": 5200000,
      "dex": ""
    },
    {
      "pair": "JitoSOL-SOL",
      "feesApy7d": 8.17,
      "volume7d": 13980000,
      "tvl": 4940000,
      "dex": ""
    },
    {
      "pair": "USDG-USX",
      "feesApy7d": 0,
      "volume7d": 0,
      "tvl": 3900000,
      "dex": ""
    },
    {
      "pair": "wYLDS-USDC",
      "feesApy7d": 0,
      "volume7d": 0,
      "tvl": 3570000,
      "dex": ""
    },
    {
      "pair": "USDu-USDC",
      "feesApy7d": 11.76,
      "volume7d": 341710,
      "tvl": 3160000,
      "dex": ""
    },
    {
      "pair": "USDG-syrupUSDC",
      "feesApy7d": 0.12,
      "volume7d": 617260,
      "tvl": 2520000,
      "dex": ""
    },
    {
      "pair": "JitoSOL-SOL",
      "feesApy7d": 9.18,
      "volume7d": 4780000,
      "tvl": 2120000,
      "dex": ""
    }
  ],
  "multiply": [
    {
      "supply": "USDeEthena Market",
      "market": "",
      "borrowToken": "USDG",
      "maxNetApy": 20.37,
      "maxLeverage": "12.5x",
      "liqAvailable": 0,
      "supplied": 32140000,
      "strategy": "RWA Loop"
    },
    {
      "supply": "STRCxSTRCx Market",
      "market": "",
      "borrowToken": "USDC",
      "maxNetApy": 17.08,
      "maxLeverage": "2x",
      "liqAvailable": 116940,
      "supplied": 727230,
      "strategy": "RWA Loop"
    },
    {
      "supply": "PRIME",
      "market": "Prime Market",
      "borrowToken": "CASH",
      "maxNetApy": 10.14,
      "maxLeverage": "8.3x",
      "liqAvailable": 10370000,
      "supplied": 24660000,
      "strategy": "RWA Loop"
    },
    {
      "supply": "PRIME",
      "market": "Prime Market",
      "borrowToken": "USDC",
      "maxNetApy": 7.9,
      "maxLeverage": "8.3x",
      "liqAvailable": 0,
      "supplied": 111120000,
      "strategy": "RWA Loop"
    },
    {
      "supply": "PRIME",
      "market": "Prime Market",
      "borrowToken": "PYUSD",
      "maxNetApy": 9.64,
      "maxLeverage": "8.3x",
      "liqAvailable": 10780000,
      "supplied": 34300000,
      "strategy": "RWA Loop"
    },
    {
      "supply": "PRIME",
      "market": "Prime Market",
      "borrowToken": "USDS",
      "maxNetApy": 4.79,
      "maxLeverage": "8.3x",
      "liqAvailable": 0,
      "supplied": 4600000,
      "strategy": "RWA Loop"
    },
    {
      "supply": "JLP",
      "market": "JLP Market",
      "borrowToken": "USDC",
      "maxNetApy": 21.33,
      "maxLeverage": "6.2x",
      "liqAvailable": 1490000,
      "supplied": 20410000,
      "strategy": "Directional Leverage"
    },
    {
      "supply": "SOL",
      "market": "Main Market",
      "borrowToken": "USDC",
      "maxNetApy": 0.25,
      "maxLeverage": "3.8x",
      "liqAvailable": 6800000,
      "supplied": 715020,
      "strategy": "Directional Leverage"
    },
    {
      "supply": "syrupUSDC",
      "market": "Maple Market",
      "borrowToken": "USDC",
      "maxNetApy": 0,
      "maxLeverage": "8.3x",
      "liqAvailable": 173590,
      "supplied": 1970000,
      "strategy": "RWA Loop"
    },
    {
      "supply": "STKESOL",
      "market": "Main Market",
      "borrowToken": "SOL",
      "maxNetApy": 22.8,
      "maxLeverage": "7.7x",
      "liqAvailable": 20810000,
      "supplied": 7890000,
      "strategy": "SOL Loop"
    },
    {
      "supply": "JITOSOL",
      "market": "Jito Market",
      "borrowToken": "SOL",
      "maxNetApy": 18.19,
      "maxLeverage": "12.5x",
      "liqAvailable": 801830,
      "supplied": 5620000,
      "strategy": "SOL Loop"
    },
    {
      "supply": "lanternSOL",
      "market": "Main Market",
      "borrowToken": "SOL",
      "maxNetApy": 11.08,
      "maxLeverage": "7.7x",
      "liqAvailable": 20810000,
      "supplied": 1860000,
      "strategy": "SOL Loop"
    },
    {
      "supply": "USDC",
      "market": "Main Market",
      "borrowToken": "PYUSD",
      "maxNetApy": 28.77,
      "maxLeverage": "10x",
      "liqAvailable": 9310000,
      "supplied": 1930000,
      "strategy": "Stable Loop"
    },
    {
      "supply": "ONyc",
      "market": "OnRe Market",
      "borrowToken": "USDC",
      "maxNetApy": 20.78,
      "maxLeverage": "2.5x",
      "liqAvailable": 5670000,
      "supplied": 56100000,
      "strategy": "RWA Loop"
    },
    {
      "supply": "ONyc",
      "market": "OnRe Market",
      "borrowToken": "USDG",
      "maxNetApy": 20.62,
      "maxLeverage": "2.5x",
      "liqAvailable": 3720,
      "supplied": 11540000,
      "strategy": "RWA Loop"
    },
    {
      "supply": "ONyc",
      "market": "OnRe Market",
      "borrowToken": "USDS",
      "maxNetApy": 19.25,
      "maxLeverage": "2.5x",
      "liqAvailable": 6030,
      "supplied": 1100000,
      "strategy": "RWA Loop"
    },
    {
      "supply": "syrupUSDC",
      "market": "Maple Market",
      "borrowToken": "USDG",
      "maxNetApy": 0,
      "maxLeverage": "8.3x",
      "liqAvailable": 30790,
      "supplied": 566830,
      "strategy": "RWA Loop"
    },
    {
      "supply": "syrupUSDC",
      "market": "Maple Market",
      "borrowToken": "USDS",
      "maxNetApy": 10.23,
      "maxLeverage": "8.3x",
      "liqAvailable": 18010,
      "supplied": 159080,
      "strategy": "RWA Loop"
    },
    {
      "supply": "syrupUSDC",
      "market": "Maple Market",
      "borrowToken": "CASH",
      "maxNetApy": 0,
      "maxLeverage": "8.3x",
      "liqAvailable": 11070,
      "supplied": 254540,
      "strategy": "RWA Loop"
    },
    {
      "supply": "syrupUSDC",
      "market": "Maple Market",
      "borrowToken": "PYUSD",
      "maxNetApy": 6.14,
      "maxLeverage": "5x",
      "liqAvailable": 7810000,
      "supplied": 50650000,
      "strategy": "RWA Loop"
    },
    {
      "supply": "USDG",
      "market": "Main Market",
      "borrowToken": "PYUSD",
      "maxNetApy": 34.19,
      "maxLeverage": "10x",
      "liqAvailable": 9310000,
      "supplied": 8900000,
      "strategy": "Stable Loop"
    },
    {
      "supply": "JLP",
      "market": "JLP Market",
      "borrowToken": "USDG",
      "maxNetApy": 18.05,
      "maxLeverage": "6.2x",
      "liqAvailable": 24100,
      "supplied": 614740,
      "strategy": "Directional Leverage"
    },
    {
      "supply": "JLP",
      "market": "JLP Market",
      "borrowToken": "USDT",
      "maxNetApy": 22.62,
      "maxLeverage": "6.2x",
      "liqAvailable": 151850,
      "supplied": 2730000,
      "strategy": "Directional Leverage"
    },
    {
      "supply": "JLP",
      "market": "JLP Market",
      "borrowToken": "PYUSD",
      "maxNetApy": 3.54,
      "maxLeverage": "6.2x",
      "liqAvailable": 39900,
      "supplied": 2040000,
      "strategy": "Directional Leverage"
    },
    {
      "supply": "eUSX",
      "market": "Solstice Market",
      "borrowToken": "USX",
      "maxNetApy": 18.03,
      "maxLeverage": "4x",
      "liqAvailable": 10420000,
      "supplied": 3320000,
      "strategy": "RWA Loop"
    },
    {
      "supply": "eUSX",
      "market": "Solstice Market",
      "borrowToken": "USDG",
      "maxNetApy": 21.95,
      "maxLeverage": "4x",
      "liqAvailable": 380670,
      "supplied": 815180,
      "strategy": "RWA Loop"
    },
    {
      "supply": "eUSX",
      "market": "Solstice Market",
      "borrowToken": "USDC",
      "maxNetApy": 12.53,
      "maxLeverage": "4x",
      "liqAvailable": 16219.999999999998,
      "supplied": 18.85,
      "strategy": "RWA Loop"
    },
    {
      "supply": "SOL",
      "market": "Main Market",
      "borrowToken": "PYUSD",
      "maxNetApy": 11.58,
      "maxLeverage": "3.8x",
      "liqAvailable": 9310000,
      "supplied": 304730,
      "strategy": "Directional Leverage"
    },
    {
      "supply": "dSOL",
      "market": "Main Market",
      "borrowToken": "SOL",
      "maxNetApy": 4.6,
      "maxLeverage": "7.7x",
      "liqAvailable": 20810000,
      "supplied": 543080,
      "strategy": "SOL Loop"
    },
    {
      "supply": "JUPSOL",
      "market": "Main Market",
      "borrowToken": "SOL",
      "maxNetApy": 3.44,
      "maxLeverage": "7.7x",
      "liqAvailable": 20810000,
      "supplied": 18590000,
      "strategy": "SOL Loop"
    },
    {
      "supply": "JUPSOL",
      "market": "Main Market",
      "borrowToken": "USDC",
      "maxNetApy": 5.08,
      "maxLeverage": "2.4x",
      "liqAvailable": 6800000,
      "supplied": 48060,
      "strategy": "Directional Leverage"
    },
    {
      "supply": "JITOSOL",
      "market": "Main Market",
      "borrowToken": "SOL",
      "maxNetApy": 1.25,
      "maxLeverage": "7.7x",
      "liqAvailable": 20810000,
      "supplied": 4770000,
      "strategy": "SOL Loop"
    },
    {
      "supply": "JITOSOL",
      "market": "Main Market",
      "borrowToken": "USDC",
      "maxNetApy": 4.38,
      "maxLeverage": "2.4x",
      "liqAvailable": 6800000,
      "supplied": 72440,
      "strategy": "Directional Leverage"
    },
    {
      "supply": "CASH",
      "market": "Main Market",
      "borrowToken": "PYUSD",
      "maxNetApy": 13.21,
      "maxLeverage": "10x",
      "liqAvailable": 9310000,
      "supplied": 220820,
      "strategy": "Stable Loop"
    },
    {
      "supply": "MSOL",
      "market": "Main Market",
      "borrowToken": "SOL",
      "maxNetApy": 4.45,
      "maxLeverage": "7.7x",
      "liqAvailable": 20810000,
      "supplied": 5070000,
      "strategy": "SOL Loop"
    },
    {
      "supply": "MSOL",
      "market": "Main Market",
      "borrowToken": "USDC",
      "maxNetApy": 5.4,
      "maxLeverage": "2.4x",
      "liqAvailable": 6800000,
      "supplied": 3240,
      "strategy": "Directional Leverage"
    },
    {
      "supply": "VSOL",
      "market": "Main Market",
      "borrowToken": "SOL",
      "maxNetApy": 0,
      "maxLeverage": "7.7x",
      "liqAvailable": 20810000,
      "supplied": 12730000,
      "strategy": "SOL Loop"
    },
    {
      "supply": "BSOL",
      "market": "Main Market",
      "borrowToken": "SOL",
      "maxNetApy": 0.52,
      "maxLeverage": "7.7x",
      "liqAvailable": 20810000,
      "supplied": 10390000,
      "strategy": "SOL Loop"
    },
    {
      "supply": "HSOL",
      "market": "Main Market",
      "borrowToken": "SOL",
      "maxNetApy": 1.91,
      "maxLeverage": "7.7x",
      "liqAvailable": 20810000,
      "supplied": 334230,
      "strategy": "SOL Loop"
    },
    {
      "supply": "bonkSOL",
      "market": "Main Market",
      "borrowToken": "SOL",
      "maxNetApy": 3.69,
      "maxLeverage": "7.7x",
      "liqAvailable": 20810000,
      "supplied": 8130000.000000001,
      "strategy": "SOL Loop"
    },
    {
      "supply": "PSOL",
      "market": "Main Market",
      "borrowToken": "SOL",
      "maxNetApy": 4.51,
      "maxLeverage": "7.7x",
      "liqAvailable": 20810000,
      "supplied": 803990,
      "strategy": "SOL Loop"
    },
    {
      "supply": "PSOL",
      "market": "Main Market",
      "borrowToken": "CASH",
      "maxNetApy": 6.79,
      "maxLeverage": "1.8x",
      "liqAvailable": 76370,
      "supplied": 9540,
      "strategy": "Directional Leverage"
    },
    {
      "supply": "CGNTSOL",
      "market": "Main Market",
      "borrowToken": "SOL",
      "maxNetApy": 2.87,
      "maxLeverage": "7.7x",
      "liqAvailable": 20810000,
      "supplied": 5490000,
      "strategy": "SOL Loop"
    },
    {
      "supply": "dfdvSOL",
      "market": "Main Market",
      "borrowToken": "SOL",
      "maxNetApy": 3.27,
      "maxLeverage": "7.7x",
      "liqAvailable": 20810000,
      "supplied": 308610,
      "strategy": "SOL Loop"
    },
    {
      "supply": "JSOL",
      "market": "Main Market",
      "borrowToken": "SOL",
      "maxNetApy": 0,
      "maxLeverage": "7.7x",
      "liqAvailable": 20810000,
      "supplied": 3680000,
      "strategy": "SOL Loop"
    },
    {
      "supply": "strongSOL",
      "market": "Main Market",
      "borrowToken": "SOL",
      "maxNetApy": 5.12,
      "maxLeverage": "7.7x",
      "liqAvailable": 20810000,
      "supplied": 3210000,
      "strategy": "SOL Loop"
    },
    {
      "supply": "BSOL",
      "market": "Solblaze Market",
      "borrowToken": "SOL",
      "maxNetApy": 5.86,
      "maxLeverage": "10x",
      "liqAvailable": 171420,
      "supplied": 3030000,
      "strategy": "SOL Loop"
    },
    {
      "supply": "LAINESOL",
      "market": "Main Market",
      "borrowToken": "SOL",
      "maxNetApy": 1.02,
      "maxLeverage": "7.7x",
      "liqAvailable": 20810000,
      "supplied": 2910000,
      "strategy": "SOL Loop"
    },
    {
      "supply": "MSOL",
      "market": "Marinade Market",
      "borrowToken": "SOL",
      "maxNetApy": 7.57,
      "maxLeverage": "10x",
      "liqAvailable": 176480,
      "supplied": 2430000,
      "strategy": "SOL Loop"
    },
    {
      "supply": "TSLA",
      "market": "xxStocks Market",
      "borrowToken": "USDC",
      "maxNetApy": 9.36,
      "maxLeverage": "2.2x",
      "liqAvailable": 245680,
      "supplied": 24020,
      "strategy": "Directional Leverage"
    },
    {
      "supply": "INF",
      "market": "Sanctum Market",
      "borrowToken": "SOL",
      "maxNetApy": 0,
      "maxLeverage": "10x",
      "liqAvailable": 4780,
      "supplied": 1060000,
      "strategy": "SOL Loop"
    },
    {
      "supply": "picoSOL",
      "market": "Main Market",
      "borrowToken": "SOL",
      "maxNetApy": 0.16,
      "maxLeverage": "7.7x",
      "liqAvailable": 20810000,
      "supplied": 709900,
      "strategy": "SOL Loop"
    },
    {
      "supply": "SPY",
      "market": "xxStocks Market",
      "borrowToken": "USDC",
      "maxNetApy": 21.31,
      "maxLeverage": "3.7x",
      "liqAvailable": 245680,
      "supplied": 22580,
      "strategy": "Directional Leverage"
    },
    {
      "supply": "QQQ",
      "market": "xxStocks Market",
      "borrowToken": "USDC",
      "maxNetApy": 16.69,
      "maxLeverage": "3.3x",
      "liqAvailable": 245680,
      "supplied": 1780,
      "strategy": "Directional Leverage"
    },
    {
      "supply": "raSOL",
      "market": "Main Market",
      "borrowToken": "SOL",
      "maxNetApy": 4.48,
      "maxLeverage": "7.7x",
      "liqAvailable": 20810000,
      "supplied": 105070,
      "strategy": "SOL Loop"
    },
    {
      "supply": "cbBTC",
      "market": "Main Market",
      "borrowToken": "USDC",
      "maxNetApy": 24.36,
      "maxLeverage": "4.8x",
      "liqAvailable": 6800000,
      "supplied": 18770,
      "strategy": "Directional Leverage"
    },
    {
      "supply": "bbSOL",
      "market": "Main Market",
      "borrowToken": "SOL",
      "maxNetApy": 0,
      "maxLeverage": "7.7x",
      "liqAvailable": 20810000,
      "supplied": 40710,
      "strategy": "SOL Loop"
    },
    {
      "supply": "xBTC",
      "market": "Main Market",
      "borrowToken": "USDC",
      "maxNetApy": 24.36,
      "maxLeverage": "4.8x",
      "liqAvailable": 6800000,
      "supplied": 1.95,
      "strategy": "Directional Leverage"
    },
    {
      "supply": "nxSOL",
      "market": "Main Market",
      "borrowToken": "SOL",
      "maxNetApy": 1.1,
      "maxLeverage": "7.7x",
      "liqAvailable": 20810000,
      "supplied": 7170,
      "strategy": "SOL Loop"
    },
    {
      "supply": "fwdSOL",
      "market": "Main Market",
      "borrowToken": "SOL",
      "maxNetApy": 3.09,
      "maxLeverage": "7.7x",
      "liqAvailable": 20810000,
      "supplied": 92.1,
      "strategy": "SOL Loop"
    }
  ]
}