{
  "timestamp": "2026-06-07T16:45:42.268Z",
  "version": 2,
  "stats": {
    "lendMarketSize": 2858354752,
    "lendVaultDeposits": 554983987,
    "liquidityDeposits": 144675839,
    "liquidityFeesGenerated": 42216551,
    "multiplyDeposits": 469449458,
    "multiplyBorrows": 361519708,
    "borrowMarketSize": 2381587092,
    "borrowActiveBorrows": 957677672
  },
  "borrow": [
    {
      "asset": "USDe",
      "market": "Prime Market",
      "totalSupply": 278980000,
      "totalBorrow": 1270,
      "liqLtv": 94,
      "supplyApy": 4.5,
      "borrowApy": 0.01
    },
    {
      "asset": "PYUSD",
      "market": "Prime Market",
      "totalSupply": 238560000,
      "totalBorrow": 173190000,
      "liqLtv": 90,
      "supplyApy": 1.25,
      "borrowApy": 1.92
    },
    {
      "asset": "USDG",
      "market": "Prime Market",
      "totalSupply": 96600000,
      "totalBorrow": 79510000,
      "liqLtv": 0,
      "supplyApy": 1.7,
      "borrowApy": 2.3
    },
    {
      "asset": "SOL",
      "market": "Main Market",
      "totalSupply": 176410000,
      "totalBorrow": 163420000,
      "liqLtv": 75,
      "supplyApy": 10.879999999999999,
      "borrowApy": 10.07
    },
    {
      "asset": "USDC",
      "market": "Main Market",
      "totalSupply": 115710000,
      "totalBorrow": 96400000,
      "liqLtv": 90,
      "supplyApy": 3.88,
      "borrowApy": 5.87
    },
    {
      "asset": "JITOSOL",
      "market": "Main Market",
      "totalSupply": 58490000,
      "totalBorrow": 426480,
      "liqLtv": 60,
      "supplyApy": 10.2,
      "borrowApy": 1.33
    },
    {
      "asset": "cbBTC",
      "market": "Main Market",
      "totalSupply": 54220000,
      "totalBorrow": 2360000,
      "liqLtv": 80,
      "supplyApy": 4.9399999999999995,
      "borrowApy": 0.25
    },
    {
      "asset": "PYUSD",
      "market": "Main Market",
      "totalSupply": 50690000,
      "totalBorrow": 43620000,
      "liqLtv": 90,
      "supplyApy": 2.59,
      "borrowApy": 4.01
    },
    {
      "asset": "JUPSOL",
      "market": "Main Market",
      "totalSupply": 40260000,
      "totalBorrow": 240130,
      "liqLtv": 60,
      "supplyApy": 5.81,
      "borrowApy": 1.32
    },
    {
      "asset": "USDG",
      "market": "Main Market",
      "totalSupply": 26330000,
      "totalBorrow": 24020000,
      "liqLtv": 90,
      "supplyApy": 5.95,
      "borrowApy": 14.1
    },
    {
      "asset": "MSOL",
      "market": "Main Market",
      "totalSupply": 22130000,
      "totalBorrow": 273250,
      "liqLtv": 60,
      "supplyApy": 6.09,
      "borrowApy": 1.36
    },
    {
      "asset": "xBTC",
      "market": "Main Market",
      "totalSupply": 12450000,
      "totalBorrow": 251490,
      "liqLtv": 80,
      "supplyApy": 6.14,
      "borrowApy": 0.12
    },
    {
      "asset": "STKESOL",
      "market": "Main Market",
      "totalSupply": 7830000,
      "totalBorrow": 0,
      "liqLtv": 55,
      "supplyApy": 8.31,
      "borrowApy": 0
    },
    {
      "asset": "USDS",
      "market": "Main Market",
      "totalSupply": 7710000,
      "totalBorrow": 4550000,
      "liqLtv": 90,
      "supplyApy": 3.64,
      "borrowApy": 4.32
    },
    {
      "asset": "USDT",
      "market": "Main Market",
      "totalSupply": 7540000,
      "totalBorrow": 5870000,
      "liqLtv": 90,
      "supplyApy": 3.39,
      "borrowApy": 5.53
    },
    {
      "asset": "FBTC",
      "market": "Main Market",
      "totalSupply": 3110000,
      "totalBorrow": 0,
      "liqLtv": 80,
      "supplyApy": 0,
      "borrowApy": 0
    },
    {
      "asset": "ETH",
      "market": "Main Market",
      "totalSupply": 2310000,
      "totalBorrow": 1420000,
      "liqLtv": 80,
      "supplyApy": 1.64,
      "borrowApy": 3.37
    },
    {
      "asset": "EURC",
      "market": "Main Market",
      "totalSupply": 677490,
      "totalBorrow": 434020,
      "liqLtv": 0,
      "supplyApy": 1.56,
      "borrowApy": 4.37
    },
    {
      "asset": "CASH",
      "market": "Main Market",
      "totalSupply": 561460,
      "totalBorrow": 417850,
      "liqLtv": 90,
      "supplyApy": 2.58,
      "borrowApy": 4.54
    },
    {
      "asset": "USD1",
      "market": "Main Market",
      "totalSupply": 41860,
      "totalBorrow": 29600,
      "liqLtv": 0,
      "supplyApy": 2.71,
      "borrowApy": 4.95
    },
    {
      "asset": "LSTs",
      "market": "Main Market",
      "totalSupply": 224940000,
      "totalBorrow": 347910,
      "liqLtv": 55,
      "supplyApy": 0,
      "borrowApy": 0
    }
  ],
  "liquidity": [
    {
      "pair": "USDS-USDC",
      "feesApy7d": 7.33,
      "volume7d": 6370000,
      "tvl": 23550000,
      "dex": ""
    },
    {
      "pair": "syrupUSDC-USDC",
      "feesApy7d": 0.54,
      "volume7d": 21730000,
      "tvl": 20160000,
      "dex": ""
    },
    {
      "pair": "PYUSD-USDC",
      "feesApy7d": 7.04,
      "volume7d": 14100000,
      "tvl": 19550000,
      "dex": ""
    },
    {
      "pair": "USDS-USDC",
      "feesApy7d": 7.32,
      "volume7d": 613660,
      "tvl": 12500000,
      "dex": ""
    },
    {
      "pair": "USDG-USDC",
      "feesApy7d": 2.36,
      "volume7d": 49770000,
      "tvl": 10540000,
      "dex": ""
    },
    {
      "pair": "PRIME-CASH",
      "feesApy7d": 1.99,
      "volume7d": 40130000,
      "tvl": 9860000,
      "dex": ""
    },
    {
      "pair": "JitoSOL-SOL",
      "feesApy7d": 9.37,
      "volume7d": 18230000,
      "tvl": 4750000,
      "dex": ""
    },
    {
      "pair": "CASH-USDC",
      "feesApy7d": 3.97,
      "volume7d": 6380000,
      "tvl": 4350000,
      "dex": ""
    },
    {
      "pair": "USDG-USX",
      "feesApy7d": 0,
      "volume7d": 0,
      "tvl": 3910000,
      "dex": ""
    },
    {
      "pair": "wYLDS-USDC",
      "feesApy7d": 0,
      "volume7d": 0,
      "tvl": 3560000,
      "dex": ""
    },
    {
      "pair": "USDu-USDC",
      "feesApy7d": 12.02,
      "volume7d": 696410,
      "tvl": 3100000,
      "dex": ""
    },
    {
      "pair": "USDG-syrupUSDC",
      "feesApy7d": 0.27,
      "volume7d": 1390000,
      "tvl": 2520000,
      "dex": ""
    },
    {
      "pair": "USDG-USDE",
      "feesApy7d": 2.76,
      "volume7d": 6530000,
      "tvl": 2180000,
      "dex": ""
    },
    {
      "pair": "JitoSOL-SOL",
      "feesApy7d": 10.14,
      "volume7d": 5920000,
      "tvl": 2049999.9999999998,
      "dex": ""
    }
  ],
  "multiply": [
    {
      "supply": "USDeEthena Market",
      "market": "",
      "borrowToken": "PYUSD",
      "maxNetApy": 34.13,
      "maxLeverage": "12.5x",
      "liqAvailable": 48660000,
      "supplied": 36260000,
      "strategy": "RWA Loop"
    },
    {
      "supply": "STRCxSTRCx Market",
      "market": "",
      "borrowToken": "USDC",
      "maxNetApy": 16.27,
      "maxLeverage": "2x",
      "liqAvailable": 58680,
      "supplied": 707360,
      "strategy": "RWA Loop"
    },
    {
      "supply": "PRIME",
      "market": "Prime Market",
      "borrowToken": "CASH",
      "maxNetApy": 14.54,
      "maxLeverage": "8.3x",
      "liqAvailable": 11320000,
      "supplied": 22940000,
      "strategy": "RWA Loop"
    },
    {
      "supply": "PRIME",
      "market": "Prime Market",
      "borrowToken": "USDC",
      "maxNetApy": 7.33,
      "maxLeverage": "8.3x",
      "liqAvailable": 0,
      "supplied": 106890000,
      "strategy": "RWA Loop"
    },
    {
      "supply": "PRIME",
      "market": "Prime Market",
      "borrowToken": "PYUSD",
      "maxNetApy": 13.94,
      "maxLeverage": "8.3x",
      "liqAvailable": 8430000,
      "supplied": 31580000,
      "strategy": "RWA Loop"
    },
    {
      "supply": "PRIME",
      "market": "Prime Market",
      "borrowToken": "USDS",
      "maxNetApy": 11.01,
      "maxLeverage": "8.3x",
      "liqAvailable": 0,
      "supplied": 3800000,
      "strategy": "RWA Loop"
    },
    {
      "supply": "JLP",
      "market": "JLP Market",
      "borrowToken": "USDC",
      "maxNetApy": 98.88,
      "maxLeverage": "6.2x",
      "liqAvailable": 2009999.9999999998,
      "supplied": 19160000,
      "strategy": "Directional Leverage"
    },
    {
      "supply": "SOL",
      "market": "Main Market",
      "borrowToken": "USDC",
      "maxNetApy": 13.46,
      "maxLeverage": "3.8x",
      "liqAvailable": 19310000,
      "supplied": 1370000,
      "strategy": "Directional Leverage"
    },
    {
      "supply": "syrupUSDC",
      "market": "Maple Market",
      "borrowToken": "USDC",
      "maxNetApy": 14.82,
      "maxLeverage": "8.3x",
      "liqAvailable": 489630,
      "supplied": 1750000,
      "strategy": "RWA Loop"
    },
    {
      "supply": "JITOSOL",
      "market": "Jito Market",
      "borrowToken": "SOL",
      "maxNetApy": 9.48,
      "maxLeverage": "12.5x",
      "liqAvailable": 0,
      "supplied": 4680000,
      "strategy": "SOL Loop"
    },
    {
      "supply": "INF",
      "market": "Sanctum Market",
      "borrowToken": "SOL",
      "maxNetApy": 6.43,
      "maxLeverage": "10x",
      "liqAvailable": 59000,
      "supplied": 1010000,
      "strategy": "SOL Loop"
    },
    {
      "supply": "MSOL",
      "market": "Marinade Market",
      "borrowToken": "SOL",
      "maxNetApy": 6.32,
      "maxLeverage": "10x",
      "liqAvailable": 150180,
      "supplied": 2390000,
      "strategy": "SOL Loop"
    },
    {
      "supply": "USDeEthena Market",
      "market": "",
      "borrowToken": "USDG",
      "maxNetApy": 29.72,
      "maxLeverage": "12.5x",
      "liqAvailable": 0,
      "supplied": 13310000,
      "strategy": "RWA Loop"
    },
    {
      "supply": "USDC",
      "market": "Main Market",
      "borrowToken": "PYUSD",
      "maxNetApy": 2.72,
      "maxLeverage": "10x",
      "liqAvailable": 7070000,
      "supplied": 1770000,
      "strategy": "Stable Loop"
    },
    {
      "supply": "ONyc",
      "market": "OnRe Market",
      "borrowToken": "USDC",
      "maxNetApy": 20.57,
      "maxLeverage": "2.5x",
      "liqAvailable": 1500000,
      "supplied": 55650000,
      "strategy": "RWA Loop"
    },
    {
      "supply": "ONyc",
      "market": "OnRe Market",
      "borrowToken": "USDG",
      "maxNetApy": 20.49,
      "maxLeverage": "2.5x",
      "liqAvailable": 0,
      "supplied": 10850000,
      "strategy": "RWA Loop"
    },
    {
      "supply": "ONyc",
      "market": "OnRe Market",
      "borrowToken": "USDS",
      "maxNetApy": 19.77,
      "maxLeverage": "2.5x",
      "liqAvailable": 118410,
      "supplied": 1100000,
      "strategy": "RWA Loop"
    },
    {
      "supply": "syrupUSDC",
      "market": "Maple Market",
      "borrowToken": "USDG",
      "maxNetApy": 0,
      "maxLeverage": "8.3x",
      "liqAvailable": 27590,
      "supplied": 567020,
      "strategy": "RWA Loop"
    },
    {
      "supply": "syrupUSDC",
      "market": "Maple Market",
      "borrowToken": "USDS",
      "maxNetApy": 13.04,
      "maxLeverage": "8.3x",
      "liqAvailable": 31790,
      "supplied": 155550,
      "strategy": "RWA Loop"
    },
    {
      "supply": "syrupUSDC",
      "market": "Maple Market",
      "borrowToken": "CASH",
      "maxNetApy": 0,
      "maxLeverage": "8.3x",
      "liqAvailable": 11870,
      "supplied": 254630,
      "strategy": "RWA Loop"
    },
    {
      "supply": "syrupUSDC",
      "market": "Maple Market",
      "borrowToken": "PYUSD",
      "maxNetApy": 7.79,
      "maxLeverage": "5x",
      "liqAvailable": 8380000.000000001,
      "supplied": 49520000,
      "strategy": "RWA Loop"
    },
    {
      "supply": "USDG",
      "market": "Main Market",
      "borrowToken": "PYUSD",
      "maxNetApy": 23.38,
      "maxLeverage": "10x",
      "liqAvailable": 7070000,
      "supplied": 10480000,
      "strategy": "Stable Loop"
    },
    {
      "supply": "JLP",
      "market": "JLP Market",
      "borrowToken": "USDG",
      "maxNetApy": 87.38,
      "maxLeverage": "6.2x",
      "liqAvailable": 18260,
      "supplied": 523190.00000000006,
      "strategy": "Directional Leverage"
    },
    {
      "supply": "JLP",
      "market": "JLP Market",
      "borrowToken": "USDT",
      "maxNetApy": 94.73,
      "maxLeverage": "6.2x",
      "liqAvailable": 130110.00000000001,
      "supplied": 2460000,
      "strategy": "Directional Leverage"
    },
    {
      "supply": "JLP",
      "market": "JLP Market",
      "borrowToken": "PYUSD",
      "maxNetApy": 82.43,
      "maxLeverage": "6.2x",
      "liqAvailable": 50380,
      "supplied": 1850000,
      "strategy": "Directional Leverage"
    },
    {
      "supply": "eUSX",
      "market": "Solstice Market",
      "borrowToken": "USX",
      "maxNetApy": 15.41,
      "maxLeverage": "4x",
      "liqAvailable": 10140000,
      "supplied": 3720000,
      "strategy": "RWA Loop"
    },
    {
      "supply": "eUSX",
      "market": "Solstice Market",
      "borrowToken": "USDG",
      "maxNetApy": 21.18,
      "maxLeverage": "4x",
      "liqAvailable": 354900,
      "supplied": 847980,
      "strategy": "RWA Loop"
    },
    {
      "supply": "eUSX",
      "market": "Solstice Market",
      "borrowToken": "USDC",
      "maxNetApy": 11.79,
      "maxLeverage": "4x",
      "liqAvailable": 12300,
      "supplied": 18.85,
      "strategy": "RWA Loop"
    },
    {
      "supply": "SOL",
      "market": "Main Market",
      "borrowToken": "PYUSD",
      "maxNetApy": 18.76,
      "maxLeverage": "3.8x",
      "liqAvailable": 7070000,
      "supplied": 311810,
      "strategy": "Directional Leverage"
    },
    {
      "supply": "dSOL",
      "market": "Main Market",
      "borrowToken": "SOL",
      "maxNetApy": 0,
      "maxLeverage": "7.7x",
      "liqAvailable": 12990000,
      "supplied": 503370,
      "strategy": "SOL Loop"
    },
    {
      "supply": "JITOSOL",
      "market": "Main Market",
      "borrowToken": "SOL",
      "maxNetApy": 0,
      "maxLeverage": "7.7x",
      "liqAvailable": 12990000,
      "supplied": 4560000,
      "strategy": "SOL Loop"
    },
    {
      "supply": "JITOSOL",
      "market": "Main Market",
      "borrowToken": "USDC",
      "maxNetApy": 5.25,
      "maxLeverage": "2.4x",
      "liqAvailable": 19310000,
      "supplied": 94510,
      "strategy": "Directional Leverage"
    },
    {
      "supply": "CASH",
      "market": "Main Market",
      "borrowToken": "PYUSD",
      "maxNetApy": 0,
      "maxLeverage": "10x",
      "liqAvailable": 7070000,
      "supplied": 228070,
      "strategy": "Stable Loop"
    },
    {
      "supply": "JUPSOL",
      "market": "Main Market",
      "borrowToken": "SOL",
      "maxNetApy": 0,
      "maxLeverage": "7.7x",
      "liqAvailable": 12990000,
      "supplied": 15320000,
      "strategy": "SOL Loop"
    },
    {
      "supply": "JUPSOL",
      "market": "Main Market",
      "borrowToken": "USDC",
      "maxNetApy": 5.72,
      "maxLeverage": "2.4x",
      "liqAvailable": 19310000,
      "supplied": 42350,
      "strategy": "Directional Leverage"
    },
    {
      "supply": "MSOL",
      "market": "Main Market",
      "borrowToken": "SOL",
      "maxNetApy": 0,
      "maxLeverage": "7.7x",
      "liqAvailable": 12990000,
      "supplied": 3690000,
      "strategy": "SOL Loop"
    },
    {
      "supply": "MSOL",
      "market": "Main Market",
      "borrowToken": "USDC",
      "maxNetApy": 6.4,
      "maxLeverage": "2.4x",
      "liqAvailable": 19310000,
      "supplied": 1700,
      "strategy": "Directional Leverage"
    },
    {
      "supply": "VSOL",
      "market": "Main Market",
      "borrowToken": "SOL",
      "maxNetApy": 0,
      "maxLeverage": "7.7x",
      "liqAvailable": 12990000,
      "supplied": 12240000,
      "strategy": "SOL Loop"
    },
    {
      "supply": "HSOL",
      "market": "Main Market",
      "borrowToken": "SOL",
      "maxNetApy": 0,
      "maxLeverage": "7.7x",
      "liqAvailable": 12990000,
      "supplied": 320760,
      "strategy": "SOL Loop"
    },
    {
      "supply": "BSOL",
      "market": "Main Market",
      "borrowToken": "SOL",
      "maxNetApy": 0,
      "maxLeverage": "7.7x",
      "liqAvailable": 12990000,
      "supplied": 10040000,
      "strategy": "SOL Loop"
    },
    {
      "supply": "STKESOL",
      "market": "Main Market",
      "borrowToken": "SOL",
      "maxNetApy": 0,
      "maxLeverage": "7.7x",
      "liqAvailable": 12990000,
      "supplied": 7600000,
      "strategy": "SOL Loop"
    },
    {
      "supply": "bonkSOL",
      "market": "Main Market",
      "borrowToken": "SOL",
      "maxNetApy": 0,
      "maxLeverage": "7.7x",
      "liqAvailable": 12990000,
      "supplied": 7800000,
      "strategy": "SOL Loop"
    },
    {
      "supply": "PSOL",
      "market": "Main Market",
      "borrowToken": "SOL",
      "maxNetApy": 0,
      "maxLeverage": "7.7x",
      "liqAvailable": 12990000,
      "supplied": 763930,
      "strategy": "SOL Loop"
    },
    {
      "supply": "PSOL",
      "market": "Main Market",
      "borrowToken": "CASH",
      "maxNetApy": 7.28,
      "maxLeverage": "1.8x",
      "liqAvailable": 143610,
      "supplied": 9010,
      "strategy": "Directional Leverage"
    },
    {
      "supply": "CGNTSOL",
      "market": "Main Market",
      "borrowToken": "SOL",
      "maxNetApy": 0,
      "maxLeverage": "7.7x",
      "liqAvailable": 12990000,
      "supplied": 5250000,
      "strategy": "SOL Loop"
    },
    {
      "supply": "dfdvSOL",
      "market": "Main Market",
      "borrowToken": "SOL",
      "maxNetApy": 0,
      "maxLeverage": "7.7x",
      "liqAvailable": 12990000,
      "supplied": 296180,
      "strategy": "SOL Loop"
    },
    {
      "supply": "JSOL",
      "market": "Main Market",
      "borrowToken": "SOL",
      "maxNetApy": 0,
      "maxLeverage": "7.7x",
      "liqAvailable": 12990000,
      "supplied": 3430000,
      "strategy": "SOL Loop"
    },
    {
      "supply": "strongSOL",
      "market": "Main Market",
      "borrowToken": "SOL",
      "maxNetApy": 0,
      "maxLeverage": "7.7x",
      "liqAvailable": 12990000,
      "supplied": 3080000,
      "strategy": "SOL Loop"
    },
    {
      "supply": "BSOL",
      "market": "Solblaze Market",
      "borrowToken": "SOL",
      "maxNetApy": 5.16,
      "maxLeverage": "10x",
      "liqAvailable": 153540,
      "supplied": 2900000,
      "strategy": "SOL Loop"
    },
    {
      "supply": "LAINESOL",
      "market": "Main Market",
      "borrowToken": "SOL",
      "maxNetApy": 0,
      "maxLeverage": "7.7x",
      "liqAvailable": 12990000,
      "supplied": 2790000,
      "strategy": "SOL Loop"
    },
    {
      "supply": "lanternSOL",
      "market": "Main Market",
      "borrowToken": "SOL",
      "maxNetApy": 0,
      "maxLeverage": "7.7x",
      "liqAvailable": 12990000,
      "supplied": 1790000,
      "strategy": "SOL Loop"
    },
    {
      "supply": "TSLA",
      "market": "xxStocks Market",
      "borrowToken": "USDC",
      "maxNetApy": 0.16,
      "maxLeverage": "2.2x",
      "liqAvailable": 673850,
      "supplied": 22190,
      "strategy": "Directional Leverage"
    },
    {
      "supply": "picoSOL",
      "market": "Main Market",
      "borrowToken": "SOL",
      "maxNetApy": 0,
      "maxLeverage": "7.7x",
      "liqAvailable": 12990000,
      "supplied": 592940,
      "strategy": "SOL Loop"
    },
    {
      "supply": "SPY",
      "market": "xxStocks Market",
      "borrowToken": "USDC",
      "maxNetApy": 2.69,
      "maxLeverage": "3.7x",
      "liqAvailable": 673850,
      "supplied": 19590,
      "strategy": "Directional Leverage"
    },
    {
      "supply": "QQQ",
      "market": "xxStocks Market",
      "borrowToken": "USDC",
      "maxNetApy": 0.72,
      "maxLeverage": "3.3x",
      "liqAvailable": 673850,
      "supplied": 1690,
      "strategy": "Directional Leverage"
    },
    {
      "supply": "raSOL",
      "market": "Main Market",
      "borrowToken": "SOL",
      "maxNetApy": 0,
      "maxLeverage": "7.7x",
      "liqAvailable": 12990000,
      "supplied": 100840,
      "strategy": "SOL Loop"
    },
    {
      "supply": "cbBTC",
      "market": "Main Market",
      "borrowToken": "USDC",
      "maxNetApy": 22.05,
      "maxLeverage": "4.8x",
      "liqAvailable": 19310000,
      "supplied": 17010,
      "strategy": "Directional Leverage"
    },
    {
      "supply": "bbSOL",
      "market": "Main Market",
      "borrowToken": "SOL",
      "maxNetApy": 0,
      "maxLeverage": "7.7x",
      "liqAvailable": 12990000,
      "supplied": 39070,
      "strategy": "SOL Loop"
    },
    {
      "supply": "xBTC",
      "market": "Main Market",
      "borrowToken": "USDC",
      "maxNetApy": 22.08,
      "maxLeverage": "4.8x",
      "liqAvailable": 19310000,
      "supplied": 1.95,
      "strategy": "Directional Leverage"
    },
    {
      "supply": "nxSOL",
      "market": "Main Market",
      "borrowToken": "SOL",
      "maxNetApy": 0,
      "maxLeverage": "7.7x",
      "liqAvailable": 12990000,
      "supplied": 6880,
      "strategy": "SOL Loop"
    },
    {
      "supply": "fwdSOL",
      "market": "Main Market",
      "borrowToken": "SOL",
      "maxNetApy": 0,
      "maxLeverage": "7.7x",
      "liqAvailable": 12990000,
      "supplied": 88.38,
      "strategy": "SOL Loop"
    }
  ]
}